Workbook
Name Alpha: Params!$E$8
Name AsOfDate: Params!$E$6
Name BankNettingSets_Header: BankNettingSets!$C$8
Name BankNS_AbsTol: BankNettingSets!$D$5
Name BankNS_RelTol: BankNettingSets!$D$6
Name BankNS_Scale: BankNettingSets!$D$4
Name BankTR_AbsTol: BankTrades!$D$5
Name BankTR_RelTol: BankTrades!$D$6
Name BankTR_Scale: BankTrades!$D$4
Name BankTrades_Header: BankTrades!$C$8
Name BasisFactor: Params!$E$17
Name Buckets_Header: Buckets!$C$5
Name BusinessDaysPerYear: Params!$E$11
Name Checks_Header: Checks!$C$5
Name DaysPerYear: Params!$E$10
Name FormulaTest_Tolerance: FormulaTest!$E$4
Name FX_Table: Params!$C$57:$E$62
Name HedgingSets_Header: HedgingSets!$C$5
Name ImportNettingSets_Header: Import_NettingSets!$C$9
Name ImportNS_File: Import_NettingSets!$D$4
Name ImportNS_LoadedAt: Import_NettingSets!$D$5
Name ImportNS_Records: Import_NettingSets!$D$6
Name ImportNS_Status: Import_NettingSets!$D$7
Name ImportTR_File: Import_Trades!$D$4
Name ImportTR_LoadedAt: Import_Trades!$D$5
Name ImportTR_Records: Import_Trades!$D$6
Name ImportTR_Status: Import_Trades!$D$7
Name ImportTrades_Header: Import_Trades!$C$9
Name IRBucketOffset: Params!$E$22
Name IRCorrBucket12: Params!$E$19
Name IRCorrBucket13: Params!$E$21
Name IRCorrBucket23: Params!$E$20
Name LambdaThresholdCO: Params!$E$25
Name LambdaThresholdIR: Params!$E$24
Name MinMaturityBD: Params!$E$12
Name MPORFloorBilateral: Params!$E$14
Name MPORFloorCleared: Params!$E$15
Name MPORFloorLarge: Params!$E$16
Name MultiplierFloor: Params!$E$9
Name NettingSets_Header: NettingSets!$C$6
Name Params_Code: Params!$C$5
Name Params_Value: Params!$E$5
Name Reconciliation_Header: Reconciliation!$C$6
Name Regime: Params!$E$23
Name ReportingCcy: Params!$E$7
Name Results_Header: Results!$C$6
Name SDFloorBD: Params!$E$13
Name SF_Table: Params!$C$28:$K$54
Name TradeCalc_Header: TradeCalc!$C$5
Name TradeReconciliation_Header: TradeReconciliation!$C$6
Name Trades_Header: Trades!$C$4
Name VolatilityFactor: Params!$E$18

Sheet README
B1: K-SACCR
B2: ReadMe
C3: Standardised approach for counterparty credit risk under EU CRR (Art. 274-280f), the default, and Basel CRE52, chosen per netting set.
C5: How to use
C6: 1. Enable macros | D6: Open the .xlsm, click "Enable Content". If Excel shows "Microsoft has blocked macros", close the file, right-click it > Properties > tick "Unblock", reopen.
C7: 2. Parameters | D7: Params: reporting date, reporting currency, default Regime (CRR or BCBS), regulatory constants, supervisory table and FX rates (units of reporting currency per 1 unit). Yellow cells are inputs.
C8: 3. Netting sets | D8: NettingSets: one row per netting set - margin flag, client-clearing role, MPOR drivers, collateral (net VM held (+) / posted (-), NICA), threshold, MTA, optional Alpha and Regime overrides, and the margin-agreement structure. Collateral is entered after haircuts, in reporting currency.
C9: 4. Trades | D9: Trades: one row per derivative leg. Dropdowns guide the classification. Amounts can be in any currency of the FX table. Legs of one economic trade share an Economic trade ID; exactly one of them (MtM leg = Y) carries the MtM.
C10: 5. Run | D10: Click "Run SA-CCR" (macro RunSACCR). Results, HedgingSets, Buckets, TradeCalc and Checks are rebuilt; Reconciliation and TradeReconciliation compare the figures entered on BankNettingSets and BankTrades with Results and TradeCalc; "Export evidence" on Reconciliation writes the evidence report of the run as a CSV file. "Validate inputs" runs the checks only: it rewrites Checks and clears the other output sheets and both reconciliations; "Clear outputs" empties the output sheets.
C11: 6. Review | D11: Checks lists every error (trade excluded, netting set withheld, run stopped), warning and information message. Reconciliation and TradeReconciliation show MATCH or DIFFERENCE for each bank figure and every netting set or trade leg that could not be compared. TestCatalogue compares the engine with published / hand-calculated reference values per regime; FormulaTest unit-tests the formula functions.
C12: 7. Regime | D12: Basel_vs_CRR lists every difference between CRE52 and the CRR, the source check status and how the workbook treats it. Regime-dependent rules are switched per netting set.
C14: Sign and input conventions
C15: Direction | D15: Long / Short in the primary risk factor. IR: Long = pay fixed (gains when rates rise). FX: Long = long the first currency of the pair. CR: Long = protection bought (as in the BCBS examples). EQ / CO: Long = long the underlying. Options: Long = bought.
C16: Sub-class | D16: IR, FX, OT: leave blank. CR: AAA ... CCC or CQS1 ... CQS6, IG_INDEX, SG_INDEX. EQ: SINGLE, INDEX. CO: ELECTRICITY, OIL_GAS, METALS, AGRICULTURAL, OTHER, CLIMATIC (CRR only). Asset class + "_" + sub-class must exist in the supervisory table; column "Regimes" restricts a row.
C17: Risk factor | D17: IR: currency (hedging set); inflation as the currency followed by -INFL, e.g. EUR-INFL, in its own hedging set [Art. 277(4)(a), 277a(1)]. FX: currency pair, e.g. EUR/USD (order is normalised and the sign adjusted); an FX option must be entered in market quote order, base first in EUR, GBP, AUD, NZD, USD, CAD, CHF, JPY (e.g. USD/JPY), with price and strike in that quote (CRE52.59 FAQ1). CR / EQ: reference entity or index name. CO: commodity type (trades with the same text are netted as one type). OT (CRR other risks): primary risk driver.
C18: Notional | D18: Positive amount; the sign comes from Direction. IR / CR: trade notional. FX: the notional of one leg, in that leg's currency (one of the pair): the foreign-currency leg or, when both legs are foreign, the larger one in reporting currency. EQ / CO: market price x units.
C19: Dates | D19: Start (S, IR/CR only; blank = already started, except for IR/CR options, which need the start of the underlying: a swaption's exercise date, the earliest one if Bermudan, or a cap's or floor's first period; CRE52.31, CRE52.42), End (E, IR/CR, also defines the IR maturity bucket), Maturity (M, maturity factor; defaults to End, then Expiry), Option expiry (T, options). Year fractions = days / DaysPerYear. Settlement type STM (settled-to-market: the contract settles its exposure and resets its value to zero on set dates; daily variation margin alone is not STM) takes a Next reset date, after the reporting date and not after M: the maturity factor then uses the time to that date, floored at 10 BD [CRE52.37(5); Art. 279c(2)]. Blank or N: no reset date. STM in a margined netting set makes it INVALID.
C20: Nature | D20: Standard, Basis (own hedging set per label, SF x 0.5, CRE52.46) or Volatility (own hedging set per label, SF x 5, CRE52.47).
C21: Options | D21: Underlying price P, strike K, supervisory vol from the table. Lambda: under CRR computed for IR and commodity options (Del. Reg. 2021/931 Art. 5); under BCBS taken from the trade (CRE52.40 FAQ). CDO: attachment A and detachment D as decimals.
C23: Methodology (per netting set) | D23: =HYPERLINK("#README!C116","One-page reference card: all formulas and parameters (below, on this sheet)") -> One-page reference card: all formulas and parameters (below, on this sheet)
C24: EAD | D24: EAD = alpha x (RC + PFE) [CRE52.1 / Art. 274(2)]; margined EAD capped at the unmargined EAD, with C = NICA only in both regimes [CRE52.2, CRE52.10; Art. 274(3), EBA Q&A 2023_6962]
C25: RC | D25: Unmargined: max(V - C, 0), C = NICA, plus the posted VM under a BCBS one-way agreement [CRE52.10] Margined: max(V - C, TH + MTA - NICA, 0), C = VM + NICA [CRE52.18]
C26: PFE | D26: PFE = multiplier x AddOn; multiplier = min(1, 5% + 95% x exp((V - C) / (2 x 95% x AddOn))) [CRE52.23]
C27: Trade level | D27: Effective notional = delta x d x MF. d = notional x SD for IR/CR, SD = (e^-0.05S - e^-0.05E)/0.05, floored at 10 BD [CRE52.34]
C28: Maturity factor | D28: Unmargined: sqrt(min(max(M, 10 BD), 1y)) [CRE52.48]; margined: 1.5 x sqrt(MPOR/250) [CRE52.52]
C29: MPOR | D29: Floor 10 BD bilateral; 5 BD (configurable) for client clearing: the clearing member in both regimes, the client under CRR only [CRE54.12; Art. 279c(1)]; 20 BD when the netting set is flagged large or illiquid (more than 5,000 trades in the previous quarter, illiquid collateral or a hard-to-replace derivative; a current count above 5,000 with the flag N only gives a warning) [CRE52.51; Art. 285(3)]; + (N - 1) for remargining every N days; the result doubled for disputes [CRE52.50-52.52; Art. 285]
C30: IR | D30: Hedging set per currency (inflation in its own set per currency); buckets on E: CRR E <= 1y, 1y < E <= 5y, E > 5y [Art. 280a]; BCBS E < 1y, 1-5y, > 5y [CRE52.57]; EN = sqrt(D1^2+D2^2+D3^2+1.4D1D2+1.4D2D3+0.6D1D3); AddOn = 0.5% x EN. BCBS only: IRBucketOffset = FALSE uses the sum of absolute bucket values [CRE52.57(5)]; a CRR netting set with IR trades is then INVALID.
C31: FX | D31: Hedging set per currency pair; AddOn = 4% x |sum effective notional| [CRE52.59]
C32: CR / EQ | D32: Entity add-on = SF x EN; AddOn = sqrt((sum rho x A)^2 + sum (1-rho^2) x A^2) [CRE52.61, 52.66]
C33: CO | D33: Hedging sets Energy (oil/gas + electricity), Metals, Agricultural, Other (+ Climatic under CRR); single-factor formula, rho = 40% [CRE52.70, Art. 277a]
C34: OT (CRR) | D34: Other risks: per hedging set AddOn = 8% x |sum effective notional| [Art. 280f]. Under BCBS an OT trade is rejected and its netting set's EAD withheld.
C36: Sheets
C37: Params | D37: Inputs - parameters, supervisory factors, FX rates
C38: NettingSets | D38: Inputs - netting sets and margin terms
C39: Trades | D39: Inputs - trade population
C40: Import_NettingSets | D40: Staging - netting sets read from a CSV file, as text, to check and correct before they replace NettingSets
C41: Import_Trades | D41: Staging - trade legs read from a CSV file, as text, to check and correct before they replace Trades
C42: Results | D42: Output - EAD per netting set, and TOTAL CRR / TOTAL BCBS rows over the VALID netting sets of each regime
C43: HedgingSets | D43: Output - hedging-set effective notionals and add-ons
C44: Buckets | D44: Output - IR maturity buckets, FX pairs, credit/equity entities, commodity types
C45: TradeCalc | D45: Output - every trade-level intermediate (S, E, M, T, SD, d, delta, MF, effective notional)
C46: Checks | D46: Output - errors (trade excluded, netting set withheld, run stopped), warnings and information
C47: BankNettingSets | D47: Inputs - the bank's own figures per netting set, to reconcile with Results; amount scale and tolerances at the top
C48: Reconciliation | D48: Output - each bank figure against Results: MATCH, DIFFERENCE, and every netting set not compared, with the reason
... C53: Basel_vs_CRR | D53: Documentation - Basel CRE52 vs EU CRR differences and workbook treatment
C55: Worksheet functions (usable in any cell)
C56: SACCR_SupervisoryDuration(S, E, [FloorYears]) | D56: Supervisory duration
C57: SACCR_MaturityFactor(M, [Margined], [MPOR_BD], [MinBD], [BDPerYear]) | D57: Maturity factor
C58: SACCR_OptionDelta(P, K, T, Vol, IsCall, IsBought, [Lambda]) | D58: Supervisory option delta
C59: SACCR_LambdaCRR(P, K, IsInterestRate, [Threshold]) | D59: EU RTS lambda shift for IR / commodity options
C60: SACCR_CDODelta(A, D, IsLong) | D60: CDO tranche delta
C61: SACCR_IREffectiveNotional(D1, D2, D3, [Rho12], [Rho23], [Rho13]) | D61: IR hedging-set effective notional
C62: SACCR_FactorAggregation(AddOns, Rhos) | D62: Credit / equity / commodity aggregation
C63: SACCR_Multiplier(VminusC, AddOn, [FloorPct]) | D63: PFE multiplier
C64: SACCR_ReplacementCost(V, C, [Margined], [TH], [MTA], [NICA]) | D64: Replacement cost
C65: SACCR_NormCDF(x) | D65: Standard normal CDF (no WorksheetFunction dependency)
C67: Scope and limitations
C68: Not covered | D68: Simplified SA-CCR and OEM (CRR Art. 281-282), CCP default-fund contributions, multi-level client structures (role MULTI is rejected), SFTs, CVA and RWA (a trade exposure to a CCP, role CCP, is calculated; its risk weight is stated on Checks, not applied); collateral haircuts (enter C after haircuts); several margin agreements in one netting set, or one agreement over several netting sets; automatic risk-driver mapping (RTS 2021/931); digital options (option legs are calculated as an ordinary option combination, without the CRR collar or the BCBS cap). The optional reductions for sold options and sold credit protection (Art. 274(5), (7)) are not applied, which gives an EAD not lower than with them.
C69: Notes | D69: CRR climatic conditions: 18%, the factor of every commodity type other than electricity [Art. 277a(1)(e)(v), 280e(5)]. Unrated single names: enter CQS3 (0.54%), CQS5 (1.6%) where Art. 128 applies, or the step mapped from an internal rating [Art. 280c(5)(a)].
C70: Collateral | D70: VM and NICA are netting-set totals in reporting currency; positive = held, negative = posted. VM held on an unmargined netting set is rejected; VM posted on one is a one-way agreement, included in C under BCBS; rejected under CRR, where such a netting set must be entered as margined (Margined = Y) [Art. 272(7a)].
C71: Unmargined cap | D71: The cap recalculates a margined netting set as unmargined: unmargined maturity factors and C = NICA in both regimes (Results columns Z-AC).
C72: Calendar | D72: Business-day amounts (MPOR, floors) use BusinessDaysPerYear (250); dates use DaysPerYear.
C73: Sample data | D73: Illustrative counterparties (NS-ALPHA, NS-GAMMA) and FX rates. BCBS-EX1..5 reproduce CRE99 / BCBS 279 Annex 4 (amounts in thousands); the other CRR-* and BCBS-* netting sets feed the TestCatalogue; DEMO-REJECTED shows how rejected trades withhold a netting set's EAD.
C75: Code
C76: Modules | D76: M_Main (macros), CORE_Engine (calculation), CORE_Reconcile (comparison with bank figures), CORE_Export (evidence report), SACCR_Formulas (public SACCR_* functions), CORE_Config (layout constants), CORE_Util (helpers). No external references: no Scripting.Dictionary, no WorksheetFunction. Supported on Microsoft 365 or Excel 2016 and later, Windows 64-bit; 32-bit is kept compiling but not certified; Mac, Excel for the web and Excel 2013 or earlier are not supported.
C78: Reference card

Sheet Params
B1: K-SACCR
B2: Parameters
C3: Each value is read through the workbook name equal to its code in column C; only the yellow values are meant to be changed.
C5: Code | D5: Description | E5: Value | F5: Reference
C6: AsOfDate | D6: Reporting (calculation) date | E6: 46295
C7: ReportingCcy | D7: Reporting currency (all amounts converted into it) | E7: EUR
C8: Alpha | D8: Alpha multiplier on (RC + PFE) | E8: 1.4 | F8: CRE52.1 / CRR Art. 274(2)
C9: MultiplierFloor | D9: Floor of the PFE multiplier | E9: 0.05 | F9: CRE52.23
C10: DaysPerYear | D10: Calendar days per year for S, E, M, T | E10: 365
C11: BusinessDaysPerYear | D11: Business days per year (MPOR, floors) | E11: 250 | F11: CRE52.49, 52.53 / CRR Art. 279c(1)
C12: MinMaturityBD | D12: Floor on M for the unmargined maturity factor (BD) | E12: 10 | F12: CRE52.48
C13: SDFloorBD | D13: Floor on the supervisory duration (BD, 0 = none) | E13: 10 | F13: CRE52.34 / CRR Art. 279b
C14: MPORFloorBilateral | D14: MPOR floor, bilateral daily-margined netting set (BD) | E14: 10 | F14: CRE52.50
C15: MPORFloorCleared | D15: MPOR floor, client clearing (BD) | E15: 5 | F15: CRE54.12 / CRR Art. 279c(1)(b)
C16: MPORFloorLarge | D16: MPOR floor, >5,000 trades, illiquid collateral or hard-to-replace derivative (BD) | E16: 20 | F16: CRE52.51 / CRR Art. 285(3)
C17: BasisFactor | D17: Supervisory factor multiplier for basis transactions | E17: 0.5 | F17: CRE52.46
C18: VolatilityFactor | D18: Supervisory factor multiplier for volatility transactions | E18: 5 | F18: CRE52.47
C19: IRCorrBucket12 | D19: IR correlation bucket 1-2 (cross term 2 x 0.7 = 1.4) | E19: 0.7 | F19: CRE52.57
C20: IRCorrBucket23 | D20: IR correlation bucket 2-3 (cross term 1.4) | E20: 0.7 | F20: CRE52.57
C21: IRCorrBucket13 | D21: IR correlation bucket 1-3 (cross term 0.6) | E21: 0.3 | F21: CRE52.57
C22: IRBucketOffset | D22: TRUE = bucket formula; FALSE = sum of absolute bucket values | E22: TRUE | F22: CRE52.57(5); CRR allows TRUE only (Art. 280a(3))
C23: Regime | D23: Default regime: CRR (EU) or BCBS (Basel CRE52); override per netting set | E23: CRR | F23: CRR = EU regime; BCBS = Basel CRE52 | I23: see Basel_vs_CRR sheet
C24: LambdaThresholdIR | D24: CRR lambda threshold, IR options (shift = max(thr - min(P,K), 0)) | E24: 0.001 | F24: Del. Reg. 2021/931 Art. 5 (am. 2025/855)
C25: LambdaThresholdCO | D25: CRR lambda threshold, commodity options (shift = max(-(1+thr) min(P,K), 0)) | E25: 0.1 | F25: Del. Reg. 2021/931 Art. 5 (am. 2025/855)
C27: Supervisory parameters (CRE52.72 / CRR Art. 279a, 280a-280f)
C28: SF_Key | D28: Asset class | E28: Category | F28: Supervisory factor | G28: Correlation | H28: Supervisory option vol | I28: Commodity hedging set | J28: Regimes | K28: Reference
C29: IR | D29: IR | F29: 0.005 | H29: 0.5 | J29: BOTH | K29: CRE52.72 / CRR Art. 280a; RTS 2021/931 Art. 5(3) (vol)
C30: FX | D30: FX | F30: 0.04 | H30: 0.15 | J30: BOTH | K30: CRE52.72 / CRR Art. 280b
C31: CR_AAA | D31: CR | E31: AAA | F31: 0.0038 | G31: 0.5 | H31: 1 | J31: BOTH | K31: CRE52.72
C32: CR_AA | D32: CR | E32: AA | F32: 0.0038 | G32: 0.5 | H32: 1 | J32: BOTH | K32: CRE52.72
C33: CR_A | D33: CR | E33: A | F33: 0.0042 | G33: 0.5 | H33: 1 | J33: BOTH | K33: CRE52.72
C34: CR_BBB | D34: CR | E34: BBB | F34: 0.0054 | G34: 0.5 | H34: 1 | J34: BOTH | K34: CRE52.72
C35: CR_BB | D35: CR | E35: BB | F35: 0.0106 | G35: 0.5 | H35: 1 | J35: BOTH | K35: CRE52.72
C36: CR_B | D36: CR | E36: B | F36: 0.016 | G36: 0.5 | H36: 1 | J36: BOTH | K36: CRE52.72
C37: CR_CCC | D37: CR | E37: CCC | F37: 0.06 | G37: 0.5 | H37: 1 | J37: BOTH | K37: CRE52.72
C38: CR_CQS1 | D38: CR | E38: CQS1 | F38: 0.0038 | G38: 0.5 | H38: 1 | J38: BOTH | K38: CRR Art. 280c Table 3
C39: CR_CQS2 | D39: CR | E39: CQS2 | F39: 0.0042 | G39: 0.5 | H39: 1 | J39: BOTH | K39: CRR Art. 280c Table 3
C40: CR_CQS3 | D40: CR | E40: CQS3 | F40: 0.0054 | G40: 0.5 | H40: 1 | J40: BOTH | K40: CRR Art. 280c Table 3
C41: CR_CQS4 | D41: CR | E41: CQS4 | F41: 0.0106 | G41: 0.5 | H41: 1 | J41: BOTH | K41: CRR Art. 280c Table 3
C42: CR_CQS5 | D42: CR | E42: CQS5 | F42: 0.016 | G42: 0.5 | H42: 1 | J42: BOTH | K42: CRR Art. 280c Table 3
... C47: EQ_INDEX | D47: EQ | E47: INDEX | F47: 0.2 | G47: 0.8 | H47: 0.75 | J47: BOTH | K47: CRE52.72 / CRR Art. 280d
C48: CO_ELECTRICITY | D48: CO | E48: ELECTRICITY | F48: 0.4 | G48: 0.4 | H48: 1.5 | I48: ENERGY | J48: BOTH | K48: CRE52.72 / CRR Art. 280e(5); RTS 2021/931 Art. 5(3) (vol)
C49: CO_OIL_GAS | D49: CO | E49: OIL_GAS | F49: 0.18 | G49: 0.4 | H49: 0.7 | I49: ENERGY | J49: BOTH | K49: CRE52.72 / CRR Art. 280e(5); RTS 2021/931 Art. 5(3) (vol)
C50: CO_METALS | D50: CO | E50: METALS | F50: 0.18 | G50: 0.4 | H50: 0.7 | I50: METALS | J50: BOTH | K50: CRE52.72 / CRR Art. 280e(5); RTS 2021/931 Art. 5(3) (vol)
C51: CO_AGRICULTURAL | D51: CO | E51: AGRICULTURAL | F51: 0.18 | G51: 0.4 | H51: 0.7 | I51: AGRICULTURAL | J51: BOTH | K51: CRE52.72 / CRR Art. 280e(5); RTS 2021/931 Art. 5(3) (vol)
C52: CO_OTHER | D52: CO | E52: OTHER | F52: 0.18 | G52: 0.4 | H52: 0.7 | I52: OTHER | J52: BOTH | K52: CRE52.72 / CRR Art. 280e(5); RTS 2021/931 Art. 5(3) (vol)
C53: CO_CLIMATIC | D53: CO | E53: CLIMATIC | F53: 0.18 | G53: 0.4 | H53: 0.7 | I53: CLIMATIC | J53: CRR | K53: CRR Art. 277(4)(b), 277a(1)(e)(v), 280e(5)
C54: OT | D54: OT | F54: 0.08 | H54: 1.5 | J54: CRR | K54: CRR Art. 280f (SF 8%), 279a Table 1 (vol 150%)
C56: FX rates (illustrative - replace with market rates)
C57: FX_Ccy | D57: Currency | E57: Units of reporting ccy per 1 unit
C58: EUR | D58: Euro | E58: 1
C59: USD | D59: US dollar | E59: 0.86
C60: GBP | D60: Pound sterling | E60: 1.16
C61: JPY | D61: Japanese yen | E61: 0.0058
C62: CHF | D62: Swiss franc | E62: 1.07
D63: Add currencies directly below the last row (no blank rows in column C).

Sheet NettingSets
B1: K-SACCR
B2: Netting sets
C3: One row per legally enforceable netting set. Collateral after haircuts, in reporting currency; VM / NICA positive = held, negative = posted. Client clearing role: N, CM (the bank is the clearing member), CLIENT, or CCP (the bank's trade exposure to a CCP, with QCCP in R and CCP retains VM in S, both blank for other roles); MULTI (multi-level client structure) is rejected. Margin agreements: blank for one agreement, or none, covering only this netting set; MIXED or SHARED declares a structure the engine rejects.
C6: NettingSetID | D6: Counterparty | E6: Margined (Y/N) | F6: Client clearing role (N / CM / CLIENT) | G6: Remargin frequency N (BD) | H6: >5,000 trades or illiquid collateral (Y/N) | I6: Margin disputes (Y/N) | J6: MPOR override (BD) | K6: Net VM held (+) / posted (-) | L6: NICA | M6: Threshold TH | N6: MTA | O6: Alpha override | P6: Regime override (blank = Params) | Q6: Margin agreements (blank / MIXED / SHARED) | R6: QCCP (Y/N) | S6: CCP retains VM, collateral not protected (Y/N)
C7: BCBS-EX1 | D7: CRE99 / BCBS 279 Annex 4 - example 1 (IR) | E7: N | F7: N | H7: N | I7: N | K7: 0 | L7: 0 | M7: 0 | N7: 0 | P7: BCBS
C8: BCBS-EX2 | D8: CRE99 / BCBS 279 Annex 4 - example 2 (credit) | E8: N | F8: N | H8: N | I8: N | K8: 0 | L8: 0 | M8: 0 | N8: 0 | P8: BCBS
C9: BCBS-EX3 | D9: CRE99 / BCBS 279 Annex 4 - example 3 (commodity) | E9: N | F9: N | H9: N | I9: N | K9: 0 | L9: 0 | M9: 0 | N9: 0 | P9: BCBS
C10: BCBS-EX4 | D10: CRE99 / BCBS 279 Annex 4 - example 4 (IR + credit) | E10: N | F10: N | H10: N | I10: N | K10: 0 | L10: 0 | M10: 0 | N10: 0 | P10: BCBS
C11: BCBS-EX5 | D11: CRE99 / BCBS 279 Annex 4 - example 5 (IR + commodity, weekly margin) | E11: Y | F11: N | G11: 5 | H11: N | I11: N | K11: 50 | L11: 150 | M11: 0 | N11: 5 | P11: BCBS
C12: CRR-EX5 | D12: Example 5 inputs under CRR (cap not binding: same EAD) | E12: Y | F12: N | G12: 5 | H12: N | I12: N | K12: 50 | L12: 150 | M12: 0 | N12: 5 | P12: CRR
C13: BCBS-VMCAP | D13: Posted-VM scenario (rejected EBA Q&A 2022_6354) - Basel cap | E13: Y | F13: N | G13: 1 | H13: N | I13: N | K13: -1300000000 | L13: 0 | M13: 0 | N13: 0 | P13: BCBS
C14: CRR-VMCAP | D14: Posted-VM scenario (rejected EBA Q&A 2022_6354) - CRR Art. 274(3) cap, EBA Q&A 2023_6962 | E14: Y | F14: N | G14: 1 | H14: N | I14: N | K14: -1300000000 | L14: 0 | M14: 0 | N14: 0 | P14: CRR
C15: CRR-EX1-1PCT | D15: Example 1 with swaption forward at 1% (EBA RTS scenario) | E15: N | F15: N | H15: N | I15: N | K15: 0 | L15: 0 | M15: 0 | N15: 0 | P15: CRR
C16: CRR-NEGIR | D16: Receiver swaption, negative forward rate - RTS lambda | E16: N | F16: N | H16: N | I16: N | K16: 0 | L16: 0 | M16: 0 | N16: 0 | P16: CRR
C17: BCBS-NEGIR | D17: Same swaption under BCBS without lambda - must be rejected | E17: N | F17: N | H17: N | I17: N | K17: 0 | L17: 0 | M17: 0 | N17: 0 | P17: BCBS
C18: CRR-NEGCO | D18: Commodity call, negative price and strike - RTS lambda | E18: N | F18: N | H18: N | I18: N | K18: 0 | L18: 0 | M18: 0 | N18: 0 | P18: CRR
C19: CRR-OTHER | D19: Other risks category (Art. 280f) - hand-checkable | E19: N | F19: N | H19: N | I19: N | K19: 0 | L19: 0 | M19: 0 | N19: 0 | P19: CRR
C20: CRR-CLIMATE | D20: Climatic-conditions hedging set (Art. 277a), factor 18% (Art. 280e(5)) | E20: N | F20: N | H20: N | I20: N | K20: 0 | L20: 0 | M20: 0 | N20: 0 | P20: CRR
C21: NS-ALPHA | D21: Alpha Bank plc (no CSA) | E21: N | F21: N | H21: N | I21: N | K21: 0 | L21: 0 | M21: 0 | N21: 0
C22: NS-GAMMA | D22: Gamma Fund Ltd (daily CSA + IM) | E22: Y | F22: N | G22: 1 | H22: N | I22: N | K22: 1500000 | L22: 2000000 | M22: 0 | N22: 250000
C23: DEMO-REJECTED | D23: Deliberately rejected trades (demo): OT-X is other risks under BCBS, A11 has matured | E23: N | F23: N | H23: N | I23: N | K23: 0 | L23: 0 | M23: 0 | N23: 0 | P23: BCBS

Sheet Trades
B1: K-SACCR
B2: Trades
C4: TradeID | D4: NettingSetID | E4: Asset class | F4: Sub-class | G4: Risk factor / reference | H4: Instrument | I4: Direction | J4: Option type | K4: Nature | L4: Basis / vol hedging-set label | M4: Notional | N4: Notional CCY | O4: MtM | P4: MtM CCY | Q4: Start date (S) | R4: End date (E) | S4: Maturity date (M) | T4: Option expiry (T) | U4: Underlying price P | V4: Strike K | W4: Lambda shift | X4: Attachment A | Y4: Detachment D | Z4: Economic trade ID | AA4: MtM leg (Y/N) | AB4: Settlement type (N/STM) | AC4: Next reset date | AD4: Comment
C5: EX1-T1 | D5: BCBS-EX1 | E5: IR | G5: USD | H5: Linear | I5: Long | K5: Standard | M5: 10000 | N5: EUR | O5: 30 | P5: EUR | R5: 49945 | S5: 49945 | AD5: 10y IRS pay fixed - Basel ex.1 trade 1
C6: EX1-T2 | D6: BCBS-EX1 | E6: IR | G6: USD | H6: Linear | I6: Short | K6: Standard | M6: 10000 | N6: EUR | O6: -20 | P6: EUR | R6: 47755 | S6: 47755 | AD6: 4y IRS receive fixed - Basel ex.1 trade 2
C7: EX1-T3 | D7: BCBS-EX1 | E7: IR | G7: EUR | H7: Option | I7: Long | J7: Put | K7: Standard | M7: 5000 | N7: EUR | O7: 50 | P7: EUR | Q7: 46660 | R7: 50310 | S7: 50310 | T7: 46660 | U7: 0.06 | V7: 0.05 | AD7: Bought 1y-into-10y receiver swaption - Basel ex.1 trade 3
C8: EX2-T1 | D8: BCBS-EX2 | E8: CR | F8: AA | G8: FIRM A | H8: Linear | I8: Long | K8: Standard | M8: 10000 | N8: EUR | O8: 20 | P8: EUR | R8: 47390 | S8: 47390 | AD8: 3y CDS protection bought
C9: EX2-T2 | D9: BCBS-EX2 | E9: CR | F9: BBB | G9: FIRM B | H9: Linear | I9: Short | K9: Standard | M9: 10000 | N9: EUR | O9: -40 | P9: EUR | R9: 48485 | S9: 48485 | AD9: 6y CDS protection sold
C10: EX2-T3 | D10: BCBS-EX2 | E10: CR | F10: IG_INDEX | G10: CDX.IG | H10: Linear | I10: Long | K10: Standard | M10: 10000 | N10: EUR | O10: 0 | P10: EUR | R10: 48120 | S10: 48120 | AD10: 5y index CDS protection bought
C11: EX3-T1 | D11: BCBS-EX3 | E11: CO | F11: OIL_GAS | G11: CRUDE OIL | H11: Linear | I11: Long | K11: Standard | M11: 10000 | N11: EUR | O11: -50 | P11: EUR | S11: 46569 | AD11: 9m WTI forward (CRE99 treats WTI and Brent as one type, crude oil)
C12: EX3-T2 | D12: BCBS-EX3 | E12: CO | F12: OIL_GAS | G12: CRUDE OIL | H12: Linear | I12: Short | K12: Standard | M12: 20000 | N12: EUR | O12: -30 | P12: EUR | S12: 47025 | AD12: 2y Brent forward
C13: EX3-T3 | D13: BCBS-EX3 | E13: CO | F13: METALS | G13: SILVER | H13: Linear | I13: Long | K13: Standard | M13: 10000 | N13: EUR | O13: 100 | P13: EUR | S13: 48120 | AD13: 5y silver forward
C14: EX4-IRT1 | D14: BCBS-EX4 | E14: IR | G14: USD | H14: Linear | I14: Long | K14: Standard | M14: 10000 | N14: EUR | O14: 30 | P14: EUR | R14: 49945 | S14: 49945 | AD14: 10y IRS pay fixed - Basel ex.1 trade 1
C15: EX4-IRT2 | D15: BCBS-EX4 | E15: IR | G15: USD | H15: Linear | I15: Short | K15: Standard | M15: 10000 | N15: EUR | O15: -20 | P15: EUR | R15: 47755 | S15: 47755 | AD15: 4y IRS receive fixed - Basel ex.1 trade 2
C16: EX4-IRT3 | D16: BCBS-EX4 | E16: IR | G16: EUR | H16: Option | I16: Long | J16: Put | K16: Standard | M16: 5000 | N16: EUR | O16: 50 | P16: EUR | Q16: 46660 | R16: 50310 | S16: 50310 | T16: 46660 | U16: 0.06 | V16: 0.05 | AD16: Bought 1y-into-10y receiver swaption - Basel ex.1 trade 3
C17: EX4-CRT1 | D17: BCBS-EX4 | E17: CR | F17: AA | G17: FIRM A | H17: Linear | I17: Long | K17: Standard | M17: 10000 | N17: EUR | O17: 20 | P17: EUR | R17: 47390 | S17: 47390 | AD17: 3y CDS protection bought
C18: EX4-CRT2 | D18: BCBS-EX4 | E18: CR | F18: BBB | G18: FIRM B | H18: Linear | I18: Short | K18: Standard | M18: 10000 | N18: EUR | O18: -40 | P18: EUR | R18: 48485 | S18: 48485 | AD18: 6y CDS protection sold
C19: EX4-CRT3 | D19: BCBS-EX4 | E19: CR | F19: IG_INDEX | G19: CDX.IG | H19: Linear | I19: Long | K19: Standard | M19: 10000 | N19: EUR | O19: 0 | P19: EUR | R19: 48120 | S19: 48120 | AD19: 5y index CDS protection bought
C20: EX5-IRT1 | D20: BCBS-EX5 | E20: IR | G20: USD | H20: Linear | I20: Long | K20: Standard | M20: 10000 | N20: EUR | O20: 30 | P20: EUR | R20: 49945 | S20: 49945 | AD20: 10y IRS pay fixed - Basel ex.1 trade 1
C21: EX5-IRT2 | D21: BCBS-EX5 | E21: IR | G21: USD | H21: Linear | I21: Short | K21: Standard | M21: 10000 | N21: EUR | O21: -20 | P21: EUR | R21: 47755 | S21: 47755 | AD21: 4y IRS receive fixed - Basel ex.1 trade 2
C22: EX5-IRT3 | D22: BCBS-EX5 | E22: IR | G22: EUR | H22: Option | I22: Long | J22: Put | K22: Standard | M22: 5000 | N22: EUR | O22: 50 | P22: EUR | Q22: 46660 | R22: 50310 | S22: 50310 | T22: 46660 | U22: 0.06 | V22: 0.05 | AD22: Bought 1y-into-10y receiver swaption - Basel ex.1 trade 3
C23: EX5-COT1 | D23: BCBS-EX5 | E23: CO | F23: OIL_GAS | G23: CRUDE OIL | H23: Linear | I23: Long | K23: Standard | M23: 10000 | N23: EUR | O23: -50 | P23: EUR | S23: 46569 | AD23: 9m WTI forward (CRE99 treats WTI and Brent as one type, crude oil)
C24: EX5-COT2 | D24: BCBS-EX5 | E24: CO | F24: OIL_GAS | G24: CRUDE OIL | H24: Linear | I24: Short | K24: Standard | M24: 20000 | N24: EUR | O24: -30 | P24: EUR | S24: 47025 | AD24: 2y Brent forward
C25: EX5-COT3 | D25: BCBS-EX5 | E25: CO | F25: METALS | G25: SILVER | H25: Linear | I25: Long | K25: Standard | M25: 10000 | N25: EUR | O25: 100 | P25: EUR | S25: 48120 | AD25: 5y silver forward
C26: EU5-IRT1 | D26: CRR-EX5 | E26: IR | G26: USD | H26: Linear | I26: Long | K26: Standard | M26: 10000 | N26: EUR | O26: 30 | P26: EUR | R26: 49945 | S26: 49945 | AD26: 10y IRS pay fixed - Basel ex.1 trade 1
C27: EU5-IRT2 | D27: CRR-EX5 | E27: IR | G27: USD | H27: Linear | I27: Short | K27: Standard | M27: 10000 | N27: EUR | O27: -20 | P27: EUR | R27: 47755 | S27: 47755 | AD27: 4y IRS receive fixed - Basel ex.1 trade 2
C28: EU5-IRT3 | D28: CRR-EX5 | E28: IR | G28: EUR | H28: Option | I28: Long | J28: Put | K28: Standard | M28: 5000 | N28: EUR | O28: 50 | P28: EUR | Q28: 46660 | R28: 50310 | S28: 50310 | T28: 46660 | U28: 0.06 | V28: 0.05 | AD28: Bought 1y-into-10y receiver swaption - Basel ex.1 trade 3
C29: EU5-COT1 | D29: CRR-EX5 | E29: CO | F29: OIL_GAS | G29: CRUDE OIL | H29: Linear | I29: Long | K29: Standard | M29: 10000 | N29: EUR | O29: -50 | P29: EUR | S29: 46569 | AD29: 9m WTI forward (CRE99 treats WTI and Brent as one type, crude oil)
C30: EU5-COT2 | D30: CRR-EX5 | E30: CO | F30: OIL_GAS | G30: CRUDE OIL | H30: Linear | I30: Short | K30: Standard | M30: 20000 | N30: EUR | O30: -30 | P30: EUR | S30: 47025 | AD30: 2y Brent forward
C31: EU5-COT3 | D31: CRR-EX5 | E31: CO | F31: METALS | G31: SILVER | H31: Linear | I31: Long | K31: Standard | M31: 10000 | N31: EUR | O31: 100 | P31: EUR | S31: 48120 | AD31: 5y silver forward
C32: EU1P-T1 | D32: CRR-EX1-1PCT | E32: IR | G32: USD | H32: Linear | I32: Long | K32: Standard | M32: 10000 | N32: EUR | O32: 30 | P32: EUR | R32: 49945 | S32: 49945 | AD32: 10y IRS pay fixed - Basel ex.1 trade 1
C33: EU1P-T2 | D33: CRR-EX1-1PCT | E33: IR | G33: USD | H33: Linear | I33: Short | K33: Standard | M33: 10000 | N33: EUR | O33: -20 | P33: EUR | R33: 47755 | S33: 47755 | AD33: 4y IRS receive fixed - Basel ex.1 trade 2
C34: EU1P-T3 | D34: CRR-EX1-1PCT | E34: IR | G34: EUR | H34: Option | I34: Long | J34: Put | K34: Standard | M34: 5000 | N34: EUR | O34: 50 | P34: EUR | Q34: 46660 | R34: 50310 | S34: 50310 | T34: 46660 | U34: 0.01 | V34: 0.05 | AD34: Swaption with forward 1% (strike 5%)
C35: VMB-1 | D35: BCBS-VMCAP | E35: IR | G35: EUR | H35: Linear | I35: Short | K35: Standard | M35: 5845000000 | N35: EUR | O35: -1100000000 | P35: EUR | R35: 49945 | S35: 49945 | AD35: 10y IRS, MtM -1.1bn, VM posted 1.3bn
C36: VMC-1 | D36: CRR-VMCAP | E36: IR | G36: EUR | H36: Linear | I36: Short | K36: Standard | M36: 5845000000 | N36: EUR | O36: -1100000000 | P36: EUR | R36: 49945 | S36: 49945 | AD36: 10y IRS, MtM -1.1bn, VM posted 1.3bn
C37: NIR-C | D37: CRR-NEGIR | E37: IR | G37: EUR | H37: Option | I37: Long | J37: Put | K37: Standard | M37: 10000 | N37: EUR | O37: 15 | P37: EUR | Q37: 46660 | R37: 48485 | S37: 48485 | T37: 46660 | U37: -0.002 | V37: 0.001 | AD37: CRR: lambda = 0.10% - (-0.20%) = 0.30%; BCBS: no lambda entered -> rejected
C38: NIR-B | D38: BCBS-NEGIR | E38: IR | G38: EUR | H38: Option | I38: Long | J38: Put | K38: Standard | M38: 10000 | N38: EUR | O38: 15 | P38: EUR | Q38: 46660 | R38: 48485 | S38: 48485 | T38: 46660 | U38: -0.002 | V38: 0.001 | AD38: CRR: lambda = 0.10% - (-0.20%) = 0.30%; BCBS: no lambda entered -> rejected
C39: NCO-1 | D39: CRR-NEGCO | E39: CO | F39: OIL_GAS | G39: WTI | H39: Option | I39: Long | J39: Call | K39: Standard | M39: 10000 | N39: EUR | O39: 40 | P39: EUR | S39: 46477 | T39: 46477 | U39: -5 | V39: -4 | AD39: lambda = -(1+0.1) x (-5) = 5.5
C40: OT-1 | D40: CRR-OTHER | E40: OT | G40: LONGEVITY INDEX X | H40: Linear | I40: Long | K40: Standard | M40: 10000 | N40: EUR | O40: 0 | P40: EUR | S40: 47025 | AD40: Longevity swap - other risks category
C41: OT-2 | D41: CRR-OTHER | E41: OT | G41: LONGEVITY INDEX X | H41: Linear | I41: Short | K41: Standard | M41: 4000 | N41: EUR | O41: 0 | P41: EUR | S41: 47390 | AD41: Same risk driver - same hedging set
C42: OT-3 | D42: CRR-OTHER | E42: OT | G42: CAT LOSS INDEX Y | H42: Linear | I42: Long | K42: Standard | M42: 5000 | N42: EUR | O42: 0 | P42: EUR | S42: 46843 | AD42: Different risk driver - own hedging set
C43: OT-X | D43: DEMO-REJECTED | E43: OT | G43: LONGEVITY INDEX X | H43: Linear | I43: Long | K43: Standard | M43: 10000 | N43: EUR | O43: 0 | P43: EUR | S43: 47025 | AD43: Other risks in a BCBS netting set - must be rejected
C44: CL-1 | D44: CRR-CLIMATE | E44: CO | F44: CLIMATIC | G44: HDD LONDON | H44: Linear | I44: Long | K44: Standard | M44: 1000 | N44: EUR | O44: 5 | P44: EUR | S44: 46477 | AD44: Heating-degree-day swap
C45: A01 | D45: NS-ALPHA | E45: IR | G45: EUR | H45: Linear | I45: Long | K45: Standard | M45: 50000000 | N45: EUR | O45: 820000 | P45: EUR | R45: 48850 | S45: 48850 | AD45: 7y EUR IRS pay fixed
C46: A02 | D46: NS-ALPHA | E46: IR | G46: EUR | H46: Linear | I46: Short | K46: Standard | M46: 30000000 | N46: EUR | O46: -210000 | P46: EUR | R46: 47025 | S46: 47025 | AD46: 2y EUR IRS receive fixed
C47: A03 | D47: NS-ALPHA | E47: IR | G47: USD | H47: Linear | I47: Short | K47: Standard | M47: 40000000 | N47: USD | O47: -1150000 | P47: USD | R47: 50675 | S47: 50675 | AD47: 12y USD IRS receive fixed
C48: A04 | D48: NS-ALPHA | E48: IR | G48: EUR | H48: Linear | I48: Long | K48: Basis | L48: EURIBOR6M/ESTR | M48: 25000000 | N48: EUR | O48: 45000 | P48: EUR | R48: 48120 | S48: 48120 | AD48: 5y basis swap - own hedging set, SF x 0.5
C49: A05 | D49: NS-ALPHA | E49: IR | G49: EUR | H49: Option | I49: Long | J49: Call | K49: Standard | M49: 20000000 | N49: EUR | O49: 310000 | P49: EUR | Q49: 47025 | R49: 48850 | S49: 48850 | T49: 47025 | U49: 0.026 | V49: 0.03 | AD49: Bought 2y-into-5y payer swaption
C50: A06 | D50: NS-ALPHA | E50: IR | G50: EUR | H50: Linear | I50: Short | K50: Standard | M50: 15000000 | N50: EUR | O50: -60000 | P50: EUR | Q50: 46660 | R50: 47755 | S50: 47755 | AD50: 1y-forward-starting 3y IRS receive fixed
C51: A07 | D51: NS-ALPHA | E51: FX | G51: EUR/USD | H51: Linear | I51: Short | K51: Standard | M51: 25000000 | N51: USD | O51: -320000 | P51: EUR | S51: 46660 | AD51: 1y FX forward: sell EUR / buy USD 25m
C52: A08 | D52: NS-ALPHA | E52: FX | G52: USD/JPY | H52: Option | I52: Long | J52: Call | K52: Standard | M52: 10000000 | N52: USD | O52: 140000 | P52: EUR | S52: 46477 | T52: 46477 | U52: 148.5 | V52: 150 | AD52: Bought 6m USD call / JPY put
C53: A09 | D53: NS-ALPHA | E53: FX | G53: USDGBP | H53: Linear | I53: Long | K53: Standard | M53: 15000000 | N53: GBP | O53: 95000 | P53: EUR | S53: 46477 | AD53: 6m forward long USD vs GBP - pair entered inverted on purpose
C54: A10 | D54: NS-ALPHA | E54: IR | G54: GBP | H54: Linear | I54: Long | K54: Standard | M54: 20000000 | N54: GBP | O54: 12000 | P54: GBP | R54: 46569 | S54: 46569 | AD54: 9m GBP swap - bucket 1, MF < 1
C55: A11 | D55: DEMO-REJECTED | E55: IR | G55: EUR | H55: Linear | I55: Long | K55: Standard | M55: 5000000 | N55: EUR | O55: 0 | P55: EUR | R55: 46265 | S55: 46265 | AD55: Deliberate input error: matured trade, shows exclusion on Checks
C56: B01 | D56: NS-GAMMA | E56: CR | F56: BBB | G56: ACME SPA | H56: Linear | I56: Long | K56: Standard | M56: 10000000 | N56: EUR | O56: -95000 | P56: EUR | R56: 48120 | S56: 48120 | AD56: 5y CDS protection bought
C57: B02 | D57: NS-GAMMA | E57: CR | F57: BBB | G57: ACME SPA | H57: Linear | I57: Short | K57: Standard | M57: 5000000 | N57: EUR | O57: 40000 | P57: EUR | R57: 47390 | S57: 47390 | AD57: 3y CDS protection sold - same entity
C58: B03 | D58: NS-GAMMA | E58: CR | F58: CQS2 | G58: OMEGA AG | H58: Linear | I58: Short | K58: Standard | M58: 8000000 | N58: EUR | O58: 120000 | P58: EUR | R58: 47755 | S58: 47755 | AD58: 4y CDS protection sold - credit quality step 2 (CRR Art. 280c)
C59: B04 | D59: NS-GAMMA | E59: CR | F59: IG_INDEX | G59: ITRAXX EUROPE S46 | H59: Linear | I59: Long | K59: Standard | M59: 25000000 | N59: EUR | O59: -210000 | P59: EUR | R59: 48120 | S59: 48120 | AD59: 5y index protection bought
C60: B05 | D60: NS-GAMMA | E60: CR | F60: IG_INDEX | G60: ITRAXX EUROPE S46 3-6% | H60: CDO | I60: Short | K60: Standard | M60: 5000000 | N60: EUR | O60: 85000 | P60: EUR | R60: 48120 | S60: 48120 | X60: 0.03 | Y60: 0.06 | AD60: 3-6% tranche protection sold
C61: B06 | D61: NS-GAMMA | E61: EQ | F61: SINGLE | G61: ENI SPA | H61: Linear | I61: Long | K61: Standard | M61: 8000000 | N61: EUR | O61: 310000 | P61: EUR | S61: 46660 | AD61: 1y equity TRS receive performance
C62: B07 | D62: NS-GAMMA | E62: EQ | F62: INDEX | G62: EURO STOXX 50 | H62: Option | I62: Short | J62: Put | K62: Standard | M62: 10000000 | N62: EUR | O62: -150000 | P62: EUR | S62: 46477 | T62: 46477 | U62: 5400 | V62: 5000 | AD62: Sold 6m index put
C63: B08 | D63: NS-GAMMA | E63: EQ | F63: SINGLE | G63: ENEL SPA | H63: Linear | I63: Short | K63: Standard | M63: 4000000 | N63: EUR | O63: -25000 | P63: EUR | S63: 46565 | AD63: 9m equity forward short
C64: B09 | D64: NS-GAMMA | E64: EQ | F64: INDEX | G64: EURO STOXX 50 | H64: Linear | I64: Long | K64: Volatility | L64: SX5E VARIANCE | M64: 1000000 | N64: EUR | O64: 18000 | P64: EUR | S64: 46660 | AD64: Variance swap - volatility hedging set, SF x 5
C65: B10 | D65: NS-GAMMA | E65: CO | F65: OIL_GAS | G65: BRENT | H65: Linear | I65: Long | K65: Standard | M65: 6000000 | N65: USD | O65: 75000 | P65: USD | S65: 46660 | AD65: 1y Brent swap
C66: B11 | D66: NS-GAMMA | E66: CO | F66: OIL_GAS | G66: WTI | H66: Linear | I66: Short | K66: Standard | M66: 3000000 | N66: USD | O66: -20000 | P66: USD | S66: 46843 | AD66: 18m WTI swap (separate type from Brent)
C67: B12 | D67: NS-GAMMA | E67: CO | F67: ELECTRICITY | G67: IT PUN BASELOAD | H67: Linear | I67: Long | K67: Standard | M67: 2000000 | N67: EUR | O67: 60000 | P67: EUR | S67: 46660 | AD67: 1y Italian power baseload swap
C68: B13 | D68: NS-GAMMA | E68: CO | F68: METALS | G68: GOLD | H68: Linear | I68: Long | K68: Standard | M68: 5000000 | N68: USD | O68: 140000 | P68: USD | S68: 47025 | AD68: 2y gold forward
C69: B14 | D69: NS-GAMMA | E69: CO | F69: AGRICULTURAL | G69: WHEAT | H69: Linear | I69: Short | K69: Standard | M69: 1500000 | N69: USD | O69: -12000 | P69: USD | S69: 46477 | AD69: 6m wheat swap

Sheet Import_NettingSets
B1: K-SACCR
B2: NettingSets CSV staging
C3: Netting sets read from a CSV file, to check and correct before they replace NettingSets. Values are kept as text, exactly as in the file. CSV line: where the record starts in the file; blank for a row added here.
C4: Source file
C5: Loaded at
C6: Records
C7: Status | D7: EMPTY | E7: Not validated. Run SA-CCR and Validate inputs read NettingSets and Trades, never this sheet.
D8: netting_set_id | E8: counterparty | F8: margined | G8: clearing_role | H8: remargin_period_business_days | I8: large_or_illiquid | J8: margin_disputes | K8: mpor_override_business_days | L8: variation_margin_net_amount | M8: independent_collateral_net_amount | N8: threshold_amount | O8: minimum_transfer_amount | P8: alpha_factor | Q8: regime_override | R8: margin_agreements | S8: qccp | T8: ccp_retains_variation_margin
C9: CSV line | D9: NettingSetID | E9: Counterparty | F9: Margined (Y/N) | G9: Client clearing role (N / CM / CLIENT) | H9: Remargin frequency N (BD) | I9: >5,000 trades or illiquid collateral (Y/N) | J9: Margin disputes (Y/N) | K9: MPOR override (BD) | L9: Net VM held (+) / posted (-) | M9: NICA | N9: Threshold TH | O9: MTA | P9: Alpha override | Q9: Regime override (blank = Params) | R9: Margin agreements (blank / MIXED / SHARED) | S9: QCCP (Y/N) | T9: CCP retains VM, collateral not protected (Y/N)

Sheet Import_Trades
B1: K-SACCR
B2: Trades CSV staging
C3: Trade legs read from a CSV file, to check and correct before they replace Trades. Values are kept as text, exactly as in the file. CSV line: where the record starts in the file; blank for a row added here.
C4: Source file
C5: Loaded at
C6: Records
C7: Status | D7: EMPTY | E7: Not validated. Run SA-CCR and Validate inputs read NettingSets and Trades, never this sheet.
D8: trade_id | E8: netting_set_id | F8: asset_class | G8: sub_class | H8: risk_factor | I8: instrument | J8: direction | K8: option_type | L8: nature | M8: hedging_set_label | N8: notional_amount | O8: notional_currency | P8: market_value_amount | Q8: market_value_currency | R8: start_date | S8: end_date | T8: maturity_date | U8: option_expiry_date | V8: underlying_price | W8: strike_price | X8: lambda_price | Y8: attachment_rate | Z8: detachment_rate | AA8: economic_trade_id | AB8: mtm_leg | AC8: settlement_type | AD8: next_reset_date | AE8: comment
C9: CSV line | D9: TradeID | E9: NettingSetID | F9: Asset class | G9: Sub-class | H9: Risk factor / reference | I9: Instrument | J9: Direction | K9: Option type | L9: Nature | M9: Basis / vol hedging-set label | N9: Notional | O9: Notional ccy | P9: MtM | Q9: MtM ccy | R9: Start date (S) | S9: End date (E) | T9: Maturity date (M) | U9: Option expiry (T) | V9: Underlying price P | W9: Strike K | X9: Lambda shift | Y9: Attachment A | Z9: Detachment D | AA9: Economic trade ID | AB9: MtM leg (Y/N) | AC9: Settlement type (N/STM) | AD9: Next reset date | AE9: Comment

Sheet Results
B1: K-SACCR
B2: Results
C4: No results yet: press Run SA-CCR.
C5: {=ResultsStatusText(SACCR_RunInputs,NettingSets!$C:$S,Trades!$C:$AC,Params!$1:$1048576)} -> No results: press Run SA-CCR.
C6: NettingSetID | D6: Counterparty | E6: Regime | F6: Margined | G6: Trades used | H6: MPOR (BD) | I6: V (sum MtM) | J6: C (VM + NICA) | K6: RC | L6: AddOn IR | M6: AddOn FX | N6: AddOn CR | O6: AddOn EQ | P6: AddOn CO | Q6: AddOn OT | R6: AddOn aggregate | S6: Multiplier | T6: PFE | U6: Alpha | V6: EAD margined | W6: EAD cap (unmargined) | X6: EAD | Y6: Cap applied | Z6: C (cap basis) | AA6: RC (cap basis) | AB6: AddOn unmargined | AC6: Multiplier (cap basis) | AD6: Status

Sheet HedgingSets
B1: K-SACCR
B2: Hedging sets
C3: Margined netting sets are shown with the margined maturity factor; column N always shows the unmargined add-on used for the EAD cap.
C5: NettingSetID | D5: Asset class | E5: Hedging set | F5: Trades | G5: D1 (<1y; CRR <=1y) | H5: D2 (1-5y) | I5: D3 (>5y) | J5: Effective notional (IR / FX / OT) | K5: Systematic: sum rho x A | L5: Idiosyncratic: sqrt(sum (1-rho^2) A^2) | M5: Hedging-set add-on | N5: Add-on unmargined | O5: Figures basis | P5: SF effective (IR / FX / OT)

Sheet Buckets
B1: K-SACCR
B2: Buckets, entities and commodity types
C3: IR: maturity bucket on E: <1Y (CRR: up to and including 1Y) / 1-5Y / >5Y. FX: currency pair. CR / EQ: reference entity. CO: commodity type. OT: primary risk driver.
C5: NettingSetID | D5: Asset class | E5: Hedging set | F5: Bucket / entity / type | G5: Trades | H5: SF (effective) | I5: Correlation | J5: Effective notional unmargined | K5: Effective notional margined | L5: Entity / type add-on unmargined | M5: Entity / type add-on margined

Sheet TradeCalc
B1: K-SACCR
B2: Trade-level calculation
C3: Every intermediate of the trade-level SA-CCR formula; excluded trades show the reason in Messages.
C5: TradeID | D5: NettingSetID | E5: Asset class | F5: Status | G5: Hedging set | H5: Bucket / entity / type | I5: SF (effective) | J5: Notional (rep ccy) | K5: MtM (rep ccy) | L5: S | M5: E | N5: M | O5: T (option) | P5: Supervisory duration | Q5: Adjusted notional d | R5: Supervisory delta | S5: MF unmargined | T5: MF margined | U5: Effective notional unmargined | V5: Effective notional margined | W5: IR bucket | X5: Stand-alone add-on | Y5: Lambda | Z5: Regime | AA5: Messages

Sheet Checks
B1: K-SACCR
B2: Checks
C3: ERROR: input rejected; the netting set's EAD is withheld (INCOMPLETE or INVALID) or the run stops. WARNING: accepted with an assumption. INFO: information only.
C5: Severity | D5: Sheet | E5: Row | F5: Reference | G5: Message

Sheet BankNettingSets
B1: K-SACCR
B2: Bank netting-set results
C3: Enter the bank's own figures per netting set. Run SA-CCR (on Results or Trades) compares them with Results on the Reconciliation sheet. A blank figure is not compared.
C4: Amount scale | D4: 1 | E4: Units of the reporting currency per bank amount: 1, 1000 (thousands) or 1000000 (millions). The multiplier is not scaled.
C5: Absolute tolerance | D5: 1 | E5: In units of the reporting currency. Not used for the multiplier.
C6: Relative tolerance | D6: 0.0001 | E6: Of the absolute bank figure; not applied when it is 0. Amounts match within either tolerance; the multiplier only within this one, or when equal.
C8: NettingSetID | D8: Regime (BCBS / CRR) | E8: EAD | F8: RC | G8: PFE | H8: AddOn aggregate | I8: AddOn IR | J8: AddOn FX | K8: AddOn CR | L8: AddOn EQ | M8: AddOn CO | N8: AddOn OT | O8: Multiplier | P8: Comment

Sheet Reconciliation
B1: K-SACCR
B2: Reconciliation
C4: No reconciliation yet: enter bank figures on BankNettingSets and press Run SA-CCR (on Results or Trades).
C5: {=ReconciliationStatusText(SACCR_ReconInputs,SACCR_RunInputs,BankNettingSets!$1:$1048576,NettingSets!$C:$S,Trades!$C:$AC,Params!$1:$1048576)} -> No reconciliation: enter bank figures on BankNettingSets and press Run SA-CCR (on Results or Trades).
C6: NettingSetID | D6: Bank row | E6: Bank regime | F6: Calculator regime | G6: Calculator status | H6: Measure | I6: Bank figure (amounts in units) | J6: Calculator figure | K6: Difference (calculator - bank) | L6: Relative difference | M6: Result | N6: Note

Sheet BankTrades
B1: K-SACCR
B2: Bank trade-leg results
C3: Enter the bank's own figures per trade leg, by Trade ID as on Trades. Run SA-CCR (on Results or Trades) compares them with TradeCalc on the TradeReconciliation sheet. A blank figure is not compared.
C4: Amount scale | D4: 1 | E4: Units of the reporting currency per bank amount: 1, 1000 (thousands) or 1000000 (millions). M, the supervisory duration, the delta and the maturity factors are not scaled.
C5: Absolute tolerance | D5: 1 | E5: In units of the reporting currency. Used for amounts only.
C6: Relative tolerance | D6: 0.0001 | E6: Of the absolute bank figure; not applied when it is 0. Amounts match within either tolerance; M, SD, delta and the maturity factors only within this one, or when equal.
C8: TradeID | D8: Notional (rep ccy) | E8: MtM (rep ccy) | F8: M (years) | G8: Supervisory duration | H8: Adjusted notional d | I8: Supervisory delta | J8: MF unmargined | K8: MF margined | L8: Effective notional unmargined | M8: Effective notional margined | N8: Stand-alone add-on | O8: Comment

Sheet TradeReconciliation
B1: K-SACCR
B2: Trade reconciliation
C4: No reconciliation yet: enter bank figures on BankTrades and press Run SA-CCR (on Results or Trades).
C5: {=TradeReconciliationStatusText(SACCR_TradeReconInputs,SACCR_RunInputs,BankTrades!$1:$1048576,NettingSets!$C:$S,Trades!$C:$AC,Params!$1:$1048576)} -> No reconciliation: enter bank figures on BankTrades and press Run SA-CCR (on Results or Trades).
C6: TradeID | D6: Bank row | E6: NettingSetID | F6: Asset class | G6: Calculator status | H6: Measure | I6: Bank figure (amounts in units) | J6: Calculator figure | K6: Difference (calculator - bank) | L6: Relative difference | M6: Result | N6: Note | O6: Economic trade ID

Sheet TestCatalogue
B1: K-SACCR
B2: Reference-test catalogue
C4: Each test reads one output cell by netting set / trade ID and column header. Basel and EU expectations are kept separate even where they coincide. Values shown are from the last run.
C6: Test | D6: Area | E6: Description | F6: Source | G6: Source status | H6: Regime | I6: Sheet | J6: Reference | K6: Metric | L6: Expected | M6: Tolerance type | N6: Tolerance | O6: Engine | P6: Difference | Q6: Result | R6: Note
C7: T01 | D7: Core - IR | E7: Example 1: adjusted notional, 10y swap | F7: CRE99 ex.1 / BCBS 279 Annex 4a | G7: Official published value (rounded) | H7: BCBS | I7: TradeCalc | J7: EX1-T1 | K7: Adjusted notional d | L7: 78694 | M7: abs | N7: 0.5 | O7: =IFERROR(INDEX(TradeCalc!$C$6:$AA$3001,MATCH($J7,TradeCalc!$C$6:$C$3001,0),MATCH($K7,TradeCalc!$C$5:$AA$5,0)),"n/a") -> 78693.868 | P7: =IF(AND(ISNUMBER(O7),ISNUMBER(L7)),O7-L7,"") -> -0.13194253 | Q7: =IF(M7="text",IF(O7&""=L7&"","PASS","FAIL"),IF(NOT(ISNUMBER(O7)),"FAIL",IF(M7="rel",IF(ABS(P7)<=N7*MAX(1,ABS(L7)),"PASS","FAIL"),IF(ABS(P7)<=N7,"PASS","FAIL")))) -> PASS
C8: T02 | D8: Core - IR | E8: Example 1: supervisory delta, swaption | F8: CRE99 ex.1 | G8: Official published value (rounded) | H8: BCBS | I8: TradeCalc | J8: EX1-T3 | K8: Supervisory delta | L8: -0.2694 | M8: abs | N8: 5e-05 | O8: =IFERROR(INDEX(TradeCalc!$C$6:$AA$3001,MATCH($J8,TradeCalc!$C$6:$C$3001,0),MATCH($K8,TradeCalc!$C$5:$AA$5,0)),"n/a") -> -0.26939522 | P8: =IF(AND(ISNUMBER(O8),ISNUMBER(L8)),O8-L8,"") -> 4.7822895e-06 | Q8: =IF(M8="text",IF(O8&""=L8&"","PASS","FAIL"),IF(NOT(ISNUMBER(O8)),"FAIL",IF(M8="rel",IF(ABS(P8)<=N8*MAX(1,ABS(L8)),"PASS","FAIL"),IF(ABS(P8)<=N8,"PASS","FAIL")))) -> PASS
C9: T03 | D9: Core - IR | E9: Example 1: IR add-on | F9: CRE99 ex.1 | G9: Official published value (rounded) | H9: BCBS | I9: Results | J9: BCBS-EX1 | K9: AddOn IR | L9: 347 | M9: abs | N9: 0.5 | O9: =IFERROR(INDEX(Results!$C$7:$AC$3002,MATCH($J9,Results!$C$7:$C$3002,0),MATCH($K9,Results!$C$6:$AC$6,0)),"n/a") -> 346.76439 | P9: =IF(AND(ISNUMBER(O9),ISNUMBER(L9)),O9-L9,"") -> -0.23561362 | Q9: =IF(M9="text",IF(O9&""=L9&"","PASS","FAIL"),IF(NOT(ISNUMBER(O9)),"FAIL",IF(M9="rel",IF(ABS(P9)<=N9*MAX(1,ABS(L9)),"PASS","FAIL"),IF(ABS(P9)<=N9,"PASS","FAIL")))) -> PASS
C10: T04 | D10: Core - IR | E10: Example 1: EAD | F10: CRE99 ex.1 | G10: Official published value (rounded) | H10: BCBS | I10: Results | J10: BCBS-EX1 | K10: EAD | L10: 569 | M10: abs | N10: 0.5 | O10: =IFERROR(INDEX(Results!$C$7:$AC$3002,MATCH($J10,Results!$C$7:$C$3002,0),MATCH($K10,Results!$C$6:$AC$6,0)),"n/a") -> 569.47014 | P10: =IF(AND(ISNUMBER(O10),ISNUMBER(L10)),O10-L10,"") -> 0.47014094 | Q10: =IF(M10="text",IF(O10&""=L10&"","PASS","FAIL"),IF(NOT(ISNUMBER(O10)),"FAIL",IF(M10="rel",IF(ABS(P10)<=N10*MAX(1,ABS(L10)),"PASS","FAIL"),IF(ABS(P10)<=N10,"PASS","FAIL")))) -> PASS
C11: T05 | D11: Core - credit | E11: Example 2: multiplier | F11: CRE99 ex.2 | G11: Official published value (rounded) | H11: BCBS | I11: Results | J11: BCBS-EX2 | K11: Multiplier | L11: 0.965 | M11: abs | N11: 0.0005 | O11: =IFERROR(INDEX(Results!$C$7:$AC$3002,MATCH($J11,Results!$C$7:$C$3002,0),MATCH($K11,Results!$C$6:$AC$6,0)),"n/a") -> 0.96520828 | P11: =IF(AND(ISNUMBER(O11),ISNUMBER(L11)),O11-L11,"") -> 0.000208281 | Q11: =IF(M11="text",IF(O11&""=L11&"","PASS","FAIL"),IF(NOT(ISNUMBER(O11)),"FAIL",IF(M11="rel",IF(ABS(P11)<=N11*MAX(1,ABS(L11)),"PASS","FAIL"),IF(ABS(P11)<=N11,"PASS","FAIL")))) -> PASS
C12: T06 | D12: Core - credit | E12: Example 2: EAD | F12: CRE99 ex.2 | G12: Official published value (rounded) | H12: BCBS | I12: Results | J12: BCBS-EX2 | K12: EAD | L12: 381 | M12: abs | N12: 0.5 | O12: =IFERROR(INDEX(Results!$C$7:$AC$3002,MATCH($J12,Results!$C$7:$C$3002,0),MATCH($K12,Results!$C$6:$AC$6,0)),"n/a") -> 381.23832 | P12: =IF(AND(ISNUMBER(O12),ISNUMBER(L12)),O12-L12,"") -> 0.23831875 | Q12: =IF(M12="text",IF(O12&""=L12&"","PASS","FAIL"),IF(NOT(ISNUMBER(O12)),"FAIL",IF(M12="rel",IF(ABS(P12)<=N12*MAX(1,ABS(L12)),"PASS","FAIL"),IF(ABS(P12)<=N12,"PASS","FAIL")))) -> PASS
C13: T07 | D13: Core - commodity | E13: Example 3: EAD | F13: CRE99 ex.3 | G13: Official published value (rounded) | H13: BCBS | I13: Results | J13: BCBS-EX3 | K13: EAD | L13: 5406 | M13: abs | N13: 2 | O13: =IFERROR(INDEX(Results!$C$7:$AC$3002,MATCH($J13,Results!$C$7:$C$3002,0),MATCH($K13,Results!$C$6:$AC$6,0)),"n/a") -> 5404.6197 | P13: =IF(AND(ISNUMBER(O13),ISNUMBER(L13)),O13-L13,"") -> -1.3803125 | Q13: =IF(M13="text",IF(O13&""=L13&"","PASS","FAIL"),IF(NOT(ISNUMBER(O13)),"FAIL",IF(M13="rel",IF(ABS(P13)<=N13*MAX(1,ABS(L13)),"PASS","FAIL"),IF(ABS(P13)<=N13,"PASS","FAIL")))) -> PASS | R13: The 9-month leg is 274 days (0.7507y), as no date gives 0.75y at 365 days: EAD 5404.62, 1.38 below the published 5406, inside tolerance 2. An input difference, not engine rounding: at exactly 0.75y (case cre99-example-3, DaysPerYear 360) the EAD is 5405.62.
C14: T08 | D14: Core - aggregation | E14: Example 4: RC | F14: CRE99 ex.4 | G14: Official published value (rounded) | H14: BCBS | I14: Results | J14: BCBS-EX4 | K14: RC | L14: 40 | M14: abs | N14: 0.5 | O14: =IFERROR(INDEX(Results!$C$7:$AC$3002,MATCH($J14,Results!$C$7:$C$3002,0),MATCH($K14,Results!$C$6:$AC$6,0)),"n/a") -> 40 | P14: =IF(AND(ISNUMBER(O14),ISNUMBER(L14)),O14-L14,"") -> 0 | Q14: =IF(M14="text",IF(O14&""=L14&"","PASS","FAIL"),IF(NOT(ISNUMBER(O14)),"FAIL",IF(M14="rel",IF(ABS(P14)<=N14*MAX(1,ABS(L14)),"PASS","FAIL"),IF(ABS(P14)<=N14,"PASS","FAIL")))) -> PASS
C15: T09 | D15: Core - aggregation | E15: Example 4: aggregate add-on (no diversification across classes) | F15: CRE99 ex.4 | G15: Official published value (rounded) | H15: BCBS | I15: Results | J15: BCBS-EX4 | K15: AddOn aggregate | L15: 629 | M15: abs | N15: 0.5 | O15: =IFERROR(INDEX(Results!$C$7:$AC$3002,MATCH($J15,Results!$C$7:$C$3002,0),MATCH($K15,Results!$C$6:$AC$6,0)),"n/a") -> 628.89322 | P15: =IF(AND(ISNUMBER(O15),ISNUMBER(L15)),O15-L15,"") -> -0.10678176 | Q15: =IF(M15="text",IF(O15&""=L15&"","PASS","FAIL"),IF(NOT(ISNUMBER(O15)),"FAIL",IF(M15="rel",IF(ABS(P15)<=N15*MAX(1,ABS(L15)),"PASS","FAIL"),IF(ABS(P15)<=N15,"PASS","FAIL")))) -> PASS
C16: T10 | D16: Core - aggregation | E16: Example 4: EAD | F16: CRE99 ex.4 | G16: Official published value (rounded) | H16: BCBS | I16: Results | J16: BCBS-EX4 | K16: EAD | L16: 936 | M16: abs | N16: 0.6 | O16: =IFERROR(INDEX(Results!$C$7:$AC$3002,MATCH($J16,Results!$C$7:$C$3002,0),MATCH($K16,Results!$C$6:$AC$6,0)),"n/a") -> 936.45051 | P16: =IF(AND(ISNUMBER(O16),ISNUMBER(L16)),O16-L16,"") -> 0.45050554 | Q16: =IF(M16="text",IF(O16&""=L16&"","PASS","FAIL"),IF(NOT(ISNUMBER(O16)),"FAIL",IF(M16="rel",IF(ABS(P16)<=N16*MAX(1,ABS(L16)),"PASS","FAIL"),IF(ABS(P16)<=N16,"PASS","FAIL")))) -> PASS | R16: Published 936 = 1.4 x (40 + 628.9), unrounded add-on (printed 629); engine 936.45
C17: T11 | D17: Core - margined | E17: Example 5: MPOR, weekly remargining | F17: CRE99 ex.5 | G17: Official published value (rounded) | H17: BCBS | I17: Results | J17: BCBS-EX5 | K17: MPOR (BD) | L17: 14 | M17: abs | N17: 0 | O17: =IFERROR(INDEX(Results!$C$7:$AC$3002,MATCH($J17,Results!$C$7:$C$3002,0),MATCH($K17,Results!$C$6:$AC$6,0)),"n/a") -> 14 | P17: =IF(AND(ISNUMBER(O17),ISNUMBER(L17)),O17-L17,"") -> 0 | Q17: =IF(M17="text",IF(O17&""=L17&"","PASS","FAIL"),IF(NOT(ISNUMBER(O17)),"FAIL",IF(M17="rel",IF(ABS(P17)<=N17*MAX(1,ABS(L17)),"PASS","FAIL"),IF(ABS(P17)<=N17,"PASS","FAIL")))) -> PASS
C18: T12 | D18: Core - margined | E18: Example 5: aggregate add-on | F18: CRE99 ex.5 | G18: Official published value (rounded) | H18: BCBS | I18: Results | J18: BCBS-EX5 | K18: AddOn aggregate | L18: 1401 | M18: abs | N18: 0.5 | O18: =IFERROR(INDEX(Results!$C$7:$AC$3002,MATCH($J18,Results!$C$7:$C$3002,0),MATCH($K18,Results!$C$6:$AC$6,0)),"n/a") -> 1400.9624 | P18: =IF(AND(ISNUMBER(O18),ISNUMBER(L18)),O18-L18,"") -> -0.037620303 | Q18: =IF(M18="text",IF(O18&""=L18&"","PASS","FAIL"),IF(NOT(ISNUMBER(O18)),"FAIL",IF(M18="rel",IF(ABS(P18)<=N18*MAX(1,ABS(L18)),"PASS","FAIL"),IF(ABS(P18)<=N18,"PASS","FAIL")))) -> PASS
C19: T13 | D19: Core - margined | E19: Example 5: multiplier | F19: CRE99 ex.5 | G19: Official published value (rounded) | H19: BCBS | I19: Results | J19: BCBS-EX5 | K19: Multiplier | L19: 0.958 | M19: abs | N19: 0.0005 | O19: =IFERROR(INDEX(Results!$C$7:$AC$3002,MATCH($J19,Results!$C$7:$C$3002,0),MATCH($K19,Results!$C$6:$AC$6,0)),"n/a") -> 0.95812333 | P19: =IF(AND(ISNUMBER(O19),ISNUMBER(L19)),O19-L19,"") -> 0.00012332739 | Q19: =IF(M19="text",IF(O19&""=L19&"","PASS","FAIL"),IF(NOT(ISNUMBER(O19)),"FAIL",IF(M19="rel",IF(ABS(P19)<=N19*MAX(1,ABS(L19)),"PASS","FAIL"),IF(ABS(P19)<=N19,"PASS","FAIL")))) -> PASS
C20: T14 | D20: Core - margined | E20: Example 5: EAD | F20: CRE99 ex.5 | G20: Official published value (rounded) | H20: BCBS | I20: Results | J20: BCBS-EX5 | K20: EAD | L20: 1879 | M20: abs | N20: 0.5 | O20: =IFERROR(INDEX(Results!$C$7:$AC$3002,MATCH($J20,Results!$C$7:$C$3002,0),MATCH($K20,Results!$C$6:$AC$6,0)),"n/a") -> 1879.2126 | P20: =IF(AND(ISNUMBER(O20),ISNUMBER(L20)),O20-L20,"") -> 0.2126315 | Q20: =IF(M20="text",IF(O20&""=L20&"","PASS","FAIL"),IF(NOT(ISNUMBER(O20)),"FAIL",IF(M20="rel",IF(ABS(P20)<=N20*MAX(1,ABS(L20)),"PASS","FAIL"),IF(ABS(P20)<=N20,"PASS","FAIL")))) -> PASS
C21: T15 | D21: EU - cap | E21: Example 5 under CRR: Art. 274(3) cap not binding, same EAD | F21: CRE99 ex.5 + CRR Art. 274(3) | G21: Illustrative - separate unreviewed calculation | H21: CRR | I21: Results | J21: CRR-EX5 | K21: EAD | L21: 1879 | M21: abs | N21: 0.5 | O21: =IFERROR(INDEX(Results!$C$7:$AC$3002,MATCH($J21,Results!$C$7:$C$3002,0),MATCH($K21,Results!$C$6:$AC$6,0)),"n/a") -> 1879.2126 | P21: =IF(AND(ISNUMBER(O21),ISNUMBER(L21)),O21-L21,"") -> 0.2126315 | Q21: =IF(M21="text",IF(O21&""=L21&"","PASS","FAIL"),IF(NOT(ISNUMBER(O21)),"FAIL",IF(M21="rel",IF(ABS(P21)<=N21*MAX(1,ABS(L21)),"PASS","FAIL"),IF(ABS(P21)<=N21,"PASS","FAIL")))) -> PASS | R21: Common core reproduces the Basel result
C22: T16 | D22: Basel - cap | E22: Posted VM: Basel cap uses NICA only -> cap binds (~41) | F22: CRE52.2, CRE52.10 | G22: Engineering scenario - not authoritative | H22: BCBS | I22: Results | J22: BCBS-VMCAP | K22: EAD | L22: 40774849 | M22: rel | N22: 1e-09 | O22: =IFERROR(INDEX(Results!$C$7:$AC$3002,MATCH($J22,Results!$C$7:$C$3002,0),MATCH($K22,Results!$C$6:$AC$6,0)),"n/a") -> 40774849 | P22: =IF(AND(ISNUMBER(O22),ISNUMBER(L22)),O22-L22,"") -> 7.4505806e-09 | Q22: =IF(M22="text",IF(O22&""=L22&"","PASS","FAIL"),IF(NOT(ISNUMBER(O22)),"FAIL",IF(M22="rel",IF(ABS(P22)<=N22*MAX(1,ABS(L22)),"PASS","FAIL"),IF(ABS(P22)<=N22,"PASS","FAIL")))) -> PASS | R22: Same as T17: both regimes cap with NICA only; cap ~41 < margined ~377
C23: T17 | D23: EU - cap | E23: Posted VM: CRR cap excludes VM from NICA -> cap binds (~41) | F23: CRR Art. 274(3), 275(1); EBA Q&A 2023_6962 | G23: Engineering scenario - not authoritative | H23: CRR | I23: Results | J23: CRR-VMCAP | K23: EAD | L23: 40774849 | M23: rel | N23: 1e-09 | O23: =IFERROR(INDEX(Results!$C$7:$AC$3002,MATCH($J23,Results!$C$7:$C$3002,0),MATCH($K23,Results!$C$6:$AC$6,0)),"n/a") -> 40774849 | P23: =IF(AND(ISNUMBER(O23),ISNUMBER(L23)),O23-L23,"") -> 7.4505806e-09 | Q23: =IF(M23="text",IF(O23&""=L23&"","PASS","FAIL"),IF(NOT(ISNUMBER(O23)),"FAIL",IF(M23="rel",IF(ABS(P23)<=N23*MAX(1,ABS(L23)),"PASS","FAIL"),IF(ABS(P23)<=N23,"PASS","FAIL")))) -> PASS | R23: Q&A 2022_6354 (rejected) illustration: 41 (cap) vs 378 (margined); this workbook ~377 (see T16)
C24: T18 | D24: EU - cap | E24: Posted VM: cap applied flag | F24: EBA Q&A 2023_6962 | G24: Engineering scenario - not authoritative | H24: CRR | I24: Results | J24: CRR-VMCAP | K24: Cap applied | L24: Y | M24: text | N24: 0 | O24: =IFERROR(INDEX(Results!$C$7:$AC$3002,MATCH($J24,Results!$C$7:$C$3002,0),MATCH($K24,Results!$C$6:$AC$6,0)),"n/a") -> Y | P24: =IF(AND(ISNUMBER(O24),ISNUMBER(L24)),O24-L24,"") | Q24: =IF(M24="text",IF(O24&""=L24&"","PASS","FAIL"),IF(NOT(ISNUMBER(O24)),"FAIL",IF(M24="rel",IF(ABS(P24)<=N24*MAX(1,ABS(L24)),"PASS","FAIL"),IF(ABS(P24)<=N24,"PASS","FAIL")))) -> PASS
C25: T19 | D25: EU - options | E25: Swaption forward 1%: EAD (lambda = 0) | F25: Illustrative; EBA RTS figures (~761) cited, source not checked | G25: Illustrative - separate unreviewed calculation | H25: CRR | I25: Results | J25: CRR-EX1-1PCT | K25: EAD | L25: 760.49393 | M25: rel | N25: 1e-09 | O25: =IFERROR(INDEX(Results!$C$7:$AC$3002,MATCH($J25,Results!$C$7:$C$3002,0),MATCH($K25,Results!$C$6:$AC$6,0)),"n/a") -> 760.49393 | P25: =IF(AND(ISNUMBER(O25),ISNUMBER(L25)),O25-L25,"") -> -1.1368684e-13 | Q25: =IF(M25="text",IF(O25&""=L25&"","PASS","FAIL"),IF(NOT(ISNUMBER(O25)),"FAIL",IF(M25="rel",IF(ABS(P25)<=N25*MAX(1,ABS(L25)),"PASS","FAIL"),IF(ABS(P25)<=N25,"PASS","FAIL")))) -> PASS | R25: Cited figures: PFE ~483, EAD ~761 - source not opened here
C26: T20 | D26: EU - options | E26: Negative forward: RTS lambda = 0.10% - min(P, K) | F26: Del. Reg. 2021/931 Art. 5 (am. 2025/855) | G26: Illustrative - unreviewed hand calculation | H26: CRR | I26: TradeCalc | J26: NIR-C | K26: Lambda | L26: 0.003 | M26: abs | N26: 1e-12 | O26: =IFERROR(INDEX(TradeCalc!$C$6:$AA$3001,MATCH($J26,TradeCalc!$C$6:$C$3001,0),MATCH($K26,TradeCalc!$C$5:$AA$5,0)),"n/a") -> 0.003 | P26: =IF(AND(ISNUMBER(O26),ISNUMBER(L26)),O26-L26,"") -> 0 | Q26: =IF(M26="text",IF(O26&""=L26&"","PASS","FAIL"),IF(NOT(ISNUMBER(O26)),"FAIL",IF(M26="rel",IF(ABS(P26)<=N26*MAX(1,ABS(L26)),"PASS","FAIL"),IF(ABS(P26)<=N26,"PASS","FAIL")))) -> PASS
C27: T21 | D27: EU - options | E27: Negative forward: supervisory delta with shift | F27: Del. Reg. 2021/931 Art. 5 | G27: Illustrative - separate unreviewed calculation | H27: CRR | I27: TradeCalc | J27: NIR-C | K27: Supervisory delta | L27: -0.99417527 | M27: rel | N27: 1e-09 | O27: =IFERROR(INDEX(TradeCalc!$C$6:$AA$3001,MATCH($J27,TradeCalc!$C$6:$C$3001,0),MATCH($K27,TradeCalc!$C$5:$AA$5,0)),"n/a") -> -0.99417527 | P27: =IF(AND(ISNUMBER(O27),ISNUMBER(L27)),O27-L27,"") -> -1.110223e-16 | Q27: =IF(M27="text",IF(O27&""=L27&"","PASS","FAIL"),IF(NOT(ISNUMBER(O27)),"FAIL",IF(M27="rel",IF(ABS(P27)<=N27*MAX(1,ABS(L27)),"PASS","FAIL"),IF(ABS(P27)<=N27,"PASS","FAIL")))) -> PASS
C28: T22 | D28: Basel - options | E28: Negative forward without lambda under BCBS is rejected | F28: CRE52.40 FAQ (lambda by judgement) | G28: Illustrative - unreviewed hand calculation | H28: BCBS | I28: TradeCalc | J28: NIR-B | K28: Status | L28: EXCLUDED | M28: text | N28: 0 | O28: =IFERROR(INDEX(TradeCalc!$C$6:$AA$3001,MATCH($J28,TradeCalc!$C$6:$C$3001,0),MATCH($K28,TradeCalc!$C$5:$AA$5,0)),"n/a") -> EXCLUDED | P28: =IF(AND(ISNUMBER(O28),ISNUMBER(L28)),O28-L28,"") | Q28: =IF(M28="text",IF(O28&""=L28&"","PASS","FAIL"),IF(NOT(ISNUMBER(O28)),"FAIL",IF(M28="rel",IF(ABS(P28)<=N28*MAX(1,ABS(L28)),"PASS","FAIL"),IF(ABS(P28)<=N28,"PASS","FAIL")))) -> PASS | R28: Enter lambda on the trade for BCBS
C29: T23 | D29: EU - options | E29: Negative commodity price: lambda = -(1 + 0.1) x min(P, K) | F29: Del. Reg. 2021/931 Art. 5 (am. 2025/855) | G29: Illustrative - unreviewed hand calculation | H29: CRR | I29: TradeCalc | J29: NCO-1 | K29: Lambda | L29: 5.5 | M29: abs | N29: 1e-12 | O29: =IFERROR(INDEX(TradeCalc!$C$6:$AA$3001,MATCH($J29,TradeCalc!$C$6:$C$3001,0),MATCH($K29,TradeCalc!$C$5:$AA$5,0)),"n/a") -> 5.5 | P29: =IF(AND(ISNUMBER(O29),ISNUMBER(L29)),O29-L29,"") -> 0 | Q29: =IF(M29="text",IF(O29&""=L29&"","PASS","FAIL"),IF(NOT(ISNUMBER(O29)),"FAIL",IF(M29="rel",IF(ABS(P29)<=N29*MAX(1,ABS(L29)),"PASS","FAIL"),IF(ABS(P29)<=N29,"PASS","FAIL")))) -> PASS
C30: T24 | D30: EU - other risks | E30: Other risks add-on = 8% x (|6,000| + |5,000|) | F30: CRR Art. 280f | G30: Illustrative - unreviewed hand calculation | H30: CRR | I30: Results | J30: CRR-OTHER | K30: AddOn OT | L30: 880 | M30: abs | N30: 1e-09 | O30: =IFERROR(INDEX(Results!$C$7:$AC$3002,MATCH($J30,Results!$C$7:$C$3002,0),MATCH($K30,Results!$C$6:$AC$6,0)),"n/a") -> 880 | P30: =IF(AND(ISNUMBER(O30),ISNUMBER(L30)),O30-L30,"") -> 0 | Q30: =IF(M30="text",IF(O30&""=L30&"","PASS","FAIL"),IF(NOT(ISNUMBER(O30)),"FAIL",IF(M30="rel",IF(ABS(P30)<=N30*MAX(1,ABS(L30)),"PASS","FAIL"),IF(ABS(P30)<=N30,"PASS","FAIL")))) -> PASS
C31: T25 | D31: EU - other risks | E31: Other risks EAD = 1.4 x 880 | F31: CRR Art. 274(2), 280f | G31: Illustrative - unreviewed hand calculation | H31: CRR | I31: Results | J31: CRR-OTHER | K31: EAD | L31: 1232 | M31: abs | N31: 1e-09 | O31: =IFERROR(INDEX(Results!$C$7:$AC$3002,MATCH($J31,Results!$C$7:$C$3002,0),MATCH($K31,Results!$C$6:$AC$6,0)),"n/a") -> 1232 | P31: =IF(AND(ISNUMBER(O31),ISNUMBER(L31)),O31-L31,"") -> 0 | Q31: =IF(M31="text",IF(O31&""=L31&"","PASS","FAIL"),IF(NOT(ISNUMBER(O31)),"FAIL",IF(M31="rel",IF(ABS(P31)<=N31*MAX(1,ABS(L31)),"PASS","FAIL"),IF(ABS(P31)<=N31,"PASS","FAIL")))) -> PASS
C32: T26 | D32: Basel - other risks | E32: Other-risks trade in a BCBS netting set is rejected | F32: CRE52 (five asset classes) | G32: Illustrative - unreviewed hand calculation | H32: BCBS | I32: TradeCalc | J32: OT-X | K32: Status | L32: EXCLUDED | M32: text | N32: 0 | O32: =IFERROR(INDEX(TradeCalc!$C$6:$AA$3001,MATCH($J32,TradeCalc!$C$6:$C$3001,0),MATCH($K32,TradeCalc!$C$5:$AA$5,0)),"n/a") -> EXCLUDED | P32: =IF(AND(ISNUMBER(O32),ISNUMBER(L32)),O32-L32,"") | Q32: =IF(M32="text",IF(O32&""=L32&"","PASS","FAIL"),IF(NOT(ISNUMBER(O32)),"FAIL",IF(M32="rel",IF(ABS(P32)<=N32*MAX(1,ABS(L32)),"PASS","FAIL"),IF(ABS(P32)<=N32,"PASS","FAIL")))) -> PASS
C33: T27 | D33: EU - mapping | E33: Climatic variable mapped to its own commodity hedging set | F33: CRR Art. 277(4)(b), 277a | G33: Illustrative - unreviewed hand calculation | H33: CRR | I33: TradeCalc | J33: CL-1 | K33: Hedging set | L33: CO|CLIMATIC|STD | M33: text | N33: 0 | O33: =IFERROR(INDEX(TradeCalc!$C$6:$AA$3001,MATCH($J33,TradeCalc!$C$6:$C$3001,0),MATCH($K33,TradeCalc!$C$5:$AA$5,0)),"n/a") -> CO|CLIMATIC|STD | P33: =IF(AND(ISNUMBER(O33),ISNUMBER(L33)),O33-L33,"") | Q33: =IF(M33="text",IF(O33&""=L33&"","PASS","FAIL"),IF(NOT(ISNUMBER(O33)),"FAIL",IF(M33="rel",IF(ABS(P33)<=N33*MAX(1,ABS(L33)),"PASS","FAIL"),IF(ABS(P33)<=N33,"PASS","FAIL")))) -> PASS | R33: SF 18%: Art. 280e(5), checked 2026-10-09
C34: T28 | D34: EU - mapping | E34: Credit quality step 2 -> SF 0.42% | F34: CRR Art. 280c Table 3 | G34: Illustrative - unreviewed hand calculation | H34: CRR | I34: TradeCalc | J34: B03 | K34: SF (effective) | L34: 0.0042 | M34: abs | N34: 1e-12 | O34: =IFERROR(INDEX(TradeCalc!$C$6:$AA$3001,MATCH($J34,TradeCalc!$C$6:$C$3001,0),MATCH($K34,TradeCalc!$C$5:$AA$5,0)),"n/a") -> 0.0042 | P34: =IF(AND(ISNUMBER(O34),ISNUMBER(L34)),O34-L34,"") -> 0 | Q34: =IF(M34="text",IF(O34&""=L34&"","PASS","FAIL"),IF(NOT(ISNUMBER(O34)),"FAIL",IF(M34="rel",IF(ABS(P34)<=N34*MAX(1,ABS(L34)),"PASS","FAIL"),IF(ABS(P34)<=N34,"PASS","FAIL")))) -> PASS
D36: Summary | E36: =COUNTIF(Q7:Q34,"PASS")&" passed, "&COUNTIF(Q7:Q34,"FAIL")&" failed of "&COUNTA(C7:C34) -> 28 passed, 0 failed of 28
D38: Source status: "Official" = published CRE99 figure, rounded (tolerance covers rounding); it validates the Basel rules. Every other row is illustrative: an unreviewed hand calculation or a separate unreviewed calculation, not published - a regression anchor, not validation.
D39: Engineering scenarios after EBA Q&A 2022_6354 (rejected) reproduce its pattern only; the decisive rule is the final Q&A 2023_6962. The EBA swaption figures of T19 (~483 / ~761) are cited, not taken from a checked source: T19 is illustrative.
D40: Not yet in the catalogue: the CRE99 margin-agreement RC examples (segregated vs non-segregated IM). Unrated names have no engine rule: they are entered as CQS3, CQS5 or the mapped step. One-way CSA, the client clearing role and the margin-agreement structures are covered by the input-validation tests run before release, not by this catalogue; several margin agreements per netting set and one agreement over several netting sets are rejected, not modelled.

Sheet FormulaTest
B1: K-SACCR
B2: Formula tests
C3: Unit tests call the SACCR_* worksheet functions (macros enabled) on the yellow inputs. Expected computes the same rule with Excel's own functions, so changing an input tests the function on new values. Portfolio tests are on TestCatalogue.
C4: Tolerance: a test passes when its Rel. diff is at most this value | E4: 1e-05
C5: Unit tests of the worksheet functions
C6: Test | D6: Arguments | E6: Input 1 | F6: Input 2 | G6: Input 3 | H6: Input 4 | I6: Input 5 | J6: Input 6 | K6: Input 7 | L6: Expected (Excel) | M6: Function (VBA) | N6: Rel. diff | O6: Result | P6: Rule
C7: Supervisory duration, S=0, E=10 | D7: S, E (years) | E7: 0 | F7: 10 | L7: =(EXP(-0.05*MAX($E7,0))-EXP(-0.05*$F7))/0.05 -> 7.8693868 | M7: {=SACCR_SupervisoryDuration($E7,$F7)} -> 7.8693868 | N7: =IFERROR(ABS(M7-L7)/MAX(1,ABS(L7)),"") -> 0 | O7: =IF(ISNUMBER(N7),IF(N7<=FormulaTest_Tolerance,"PASS","FAIL"),"FAIL") -> PASS | P7: CRE52.34; CRR Art. 279b(1)(a)
C8: Supervisory duration, S=1, E=11 | D8: S, E (years) | E8: 1 | F8: 11 | L8: =(EXP(-0.05*MAX($E8,0))-EXP(-0.05*$F8))/0.05 -> 7.4855923 | M8: {=SACCR_SupervisoryDuration($E8,$F8)} -> 7.4855923 | N8: =IFERROR(ABS(M8-L8)/MAX(1,ABS(L8)),"") -> 0 | O8: =IF(ISNUMBER(N8),IF(N8<=FormulaTest_Tolerance,"PASS","FAIL"),"FAIL") -> PASS | P8: CRE52.34; CRR Art. 279b(1)(a)
C9: SD floor, S=0, E=0.01 (floor 10/250) | D9: S, E, floor (years) | E9: 0 | F9: 0.01 | G9: =10/250 -> 0.04 | L9: =MAX((EXP(-0.05*MAX($E9,0))-EXP(-0.05*$F9))/0.05,$G9) -> 0.04 | M9: {=SACCR_SupervisoryDuration($E9,$F9,$G9)} -> 0.04 | N9: =IFERROR(ABS(M9-L9)/MAX(1,ABS(L9)),"") -> 0 | O9: =IF(ISNUMBER(N9),IF(N9<=FormulaTest_Tolerance,"PASS","FAIL"),"FAIL") -> PASS | P9: CRE52.34; CRR Art. 279b(1)(a)
C10: MF unmargined, M=0.75 | D10: M (years) | E10: 0.75 | L10: =SQRT(MIN(MAX($E10,10/250),1)) -> 0.8660254 | M10: {=SACCR_MaturityFactor($E10)} -> 0.8660254 | N10: =IFERROR(ABS(M10-L10)/MAX(1,ABS(L10)),"") -> 0 | O10: =IF(ISNUMBER(N10),IF(N10<=FormulaTest_Tolerance,"PASS","FAIL"),"FAIL") -> PASS | P10: CRE52.48; CRR Art. 279c(1)(a)
C11: MF unmargined, M=3 days (floor 10 BD) | D11: M (years) | E11: =3/365 -> 0.0082191781 | L11: =SQRT(MIN(MAX($E11,10/250),1)) -> 0.2 | M11: {=SACCR_MaturityFactor($E11)} -> 0.2 | N11: =IFERROR(ABS(M11-L11)/MAX(1,ABS(L11)),"") -> 0 | O11: =IF(ISNUMBER(N11),IF(N11<=FormulaTest_Tolerance,"PASS","FAIL"),"FAIL") -> PASS | P11: CRE52.48; CRR Art. 279c(1)(a)
C12: MF margined, MPOR=10 BD | D12: M (years), margined, MPOR (business days) | E12: 0 | F12: TRUE | G12: 10 | L12: =IF($F12,1.5*SQRT($G12/250),SQRT(MIN(MAX($E12,10/250),1))) -> 0.3 | M12: {=SACCR_MaturityFactor($E12,$F12,$G12)} -> 0.3 | N12: =IFERROR(ABS(M12-L12)/MAX(1,ABS(L12)),"") -> 0 | O12: =IF(ISNUMBER(N12),IF(N12<=FormulaTest_Tolerance,"PASS","FAIL"),"FAIL") -> PASS | P12: CRE52.52; CRR Art. 279c(1)(b)
C13: Delta, bought put P=6% K=5% T=1 vol=50% | D13: P, K, T, volatility, call, bought | E13: 0.06 | F13: 0.05 | G13: 1 | H13: 0.5 | I13: FALSE | J13: TRUE | L13: =IF($I13,_xlfn.NORM.S.DIST((LN(($E13+$K13)/($F13+$K13))+$H13^2*$G13/2)/($H13*SQRT($G13)),TRUE),-_xlfn.NORM.S.DIST(-(LN(($E13+$K13)/($F13+$K13))+$H13^2*$G13/2)/($H13*SQRT($G13)),TRUE))*IF($J13,1,-1) -> -0.26939522 | M13: {=SACCR_OptionDelta($E13,$F13,$G13,$H13,$I13,$J13)} -> -0.26939522 | N13: =IFERROR(ABS(M13-L13)/MAX(1,ABS(L13)),"") -> 0 | O13: =IF(ISNUMBER(N13),IF(N13<=FormulaTest_Tolerance,"PASS","FAIL"),"FAIL") -> PASS | P13: CRE52.40; CRR-RTS Art. 5(1) (lambda 0 here)
C14: Delta, sold call P=100 K=110 T=0.5 vol=32% | D14: P, K, T, volatility, call, bought | E14: 100 | F14: 110 | G14: 0.5 | H14: 0.32 | I14: TRUE | J14: FALSE | L14: =IF($I14,_xlfn.NORM.S.DIST((LN(($E14+$K14)/($F14+$K14))+$H14^2*$G14/2)/($H14*SQRT($G14)),TRUE),-_xlfn.NORM.S.DIST(-(LN(($E14+$K14)/($F14+$K14))+$H14^2*$G14/2)/($H14*SQRT($G14)),TRUE))*IF($J14,1,-1) -> -0.37901135 | M14: {=SACCR_OptionDelta($E14,$F14,$G14,$H14,$I14,$J14)} -> -0.37901135 | N14: =IFERROR(ABS(M14-L14)/MAX(1,ABS(L14)),"") -> 5.5511151e-17 | O14: =IF(ISNUMBER(N14),IF(N14<=FormulaTest_Tolerance,"PASS","FAIL"),"FAIL") -> PASS | P14: CRE52.40; CRR Art. 279a(1)(a)
C15: Delta with lambda shift, P=-0.2% K=0.1% L=1% | D15: P, K, T, volatility, call, bought, lambda | E15: -0.002 | F15: 0.001 | G15: 2 | H15: 0.5 | I15: TRUE | J15: TRUE | K15: 0.01 | L15: =IF($I15,_xlfn.NORM.S.DIST((LN(($E15+$K15)/($F15+$K15))+$H15^2*$G15/2)/($H15*SQRT($G15)),TRUE),-_xlfn.NORM.S.DIST(-(LN(($E15+$K15)/($F15+$K15))+$H15^2*$G15/2)/($H15*SQRT($G15)),TRUE))*IF($J15,1,-1) -> 0.46143936 | M15: {=SACCR_OptionDelta($E15,$F15,$G15,$H15,$I15,$J15,$K15)} -> 0.46143936 | N15: =IFERROR(ABS(M15-L15)/MAX(1,ABS(L15)),"") -> 5.5511151e-17 | O15: =IF(ISNUMBER(N15),IF(N15<=FormulaTest_Tolerance,"PASS","FAIL"),"FAIL") -> PASS | P15: CRE52.40 FAQ; CRR-RTS Art. 5(1)
C16: CDO delta, 3-6% tranche, protection bought | D16: A, D, long | E16: 0.03 | F16: 0.06 | G16: TRUE | L16: =15/((1+14*$E16)*(1+14*$F16))*IF($G16,1,-1) -> 5.7409675 | M16: {=SACCR_CDODelta($E16,$F16,$G16)} -> 5.7409675 | N16: =IFERROR(ABS(M16-L16)/MAX(1,ABS(L16)),"") -> 1.5470884e-16 | O16: =IF(ISNUMBER(N16),IF(N16<=FormulaTest_Tolerance,"PASS","FAIL"),"FAIL") -> PASS | P16: CRE52.41; CRR Art. 279a(1)(b)
C17: IR effective notional, Basel ex.1 USD | D17: D1, D2, D3 (bucket effective notionals) | E17: 0 | F17: -36253.849 | G17: 78693.868 | L17: =SQRT(MAX($E17^2+$F17^2+$G17^2+1.4*$E17*$F17+1.4*$F17*$G17+0.6*$E17*$G17,0)) -> 59269.963 | M17: {=SACCR_IREffectiveNotional($E17,$F17,$G17)} -> 59269.963 | N17: =IFERROR(ABS(M17-L17)/MAX(1,ABS(L17)),"") -> 0 | O17: =IF(ISNUMBER(N17),IF(N17<=FormulaTest_Tolerance,"PASS","FAIL"),"FAIL") -> PASS | P17: CRE52.57(5); CRR Art. 280a
C18: Factor aggregation, Basel ex.2 | D18: Add-ons A1, A2, A3, correlations 1, 2, 3 | E18: 105.86194 | F18: -279.91632 | G18: 168.1114 | H18: 0.5 | I18: 0.5 | J18: 0.8 | L18: =SQRT(SUMPRODUCT($E18:$G18,$H18:$J18)^2+SUMPRODUCT((1-$H18:$J18^2)*$E18:$G18^2)) -> 282.12883 | M18: {=SACCR_FactorAggregation($E18:$G18,$H18:$J18)} -> 282.12883 | N18: =IFERROR(ABS(M18-L18)/MAX(1,ABS(L18)),"") -> 0 | O18: =IF(ISNUMBER(N18),IF(N18<=FormulaTest_Tolerance,"PASS","FAIL"),"FAIL") -> PASS | P18: CRE52.61; CRR Art. 280c
C19: Multiplier, V-C=-20, AddOn=282 | D19: V - C, add-on | E19: -20 | F19: 282 | L19: =IF(OR($F19<=0,$E19>0),1,MIN(1,0.05+0.95*EXP($E19/(2*0.95*$F19)))) -> 0.96519268 | M19: {=SACCR_Multiplier($E19,$F19)} -> 0.96519268 | N19: =IFERROR(ABS(M19-L19)/MAX(1,ABS(L19)),"") -> 0 | O19: =IF(ISNUMBER(N19),IF(N19<=FormulaTest_Tolerance,"PASS","FAIL"),"FAIL") -> PASS | P19: CRE52.23; CRR Art. 278(3)
C20: Multiplier, V-C>0 | D20: V - C, add-on | E20: 10 | F20: 282 | L20: =IF(OR($F20<=0,$E20>0),1,MIN(1,0.05+0.95*EXP($E20/(2*0.95*$F20)))) -> 1 | M20: {=SACCR_Multiplier($E20,$F20)} -> 1 | N20: =IFERROR(ABS(M20-L20)/MAX(1,ABS(L20)),"") -> 0 | O20: =IF(ISNUMBER(N20),IF(N20<=FormulaTest_Tolerance,"PASS","FAIL"),"FAIL") -> PASS | P20: CRE52.23; CRR Art. 278(3)
C21: RC margined, V-C=-5, TH=0, MTA=10, NICA=2 | D21: V, C, margined, TH, MTA, NICA | E21: 5 | F21: 10 | G21: TRUE | H21: 0 | I21: 10 | J21: 2 | L21: =IF($G21,MAX($E21-$F21,$H21+$I21-$J21,0),MAX($E21-$F21,0)) -> 8 | M21: {=SACCR_ReplacementCost($E21,$F21,$G21,$H21,$I21,$J21)} -> 8 | N21: =IFERROR(ABS(M21-L21)/MAX(1,ABS(L21)),"") -> 0 | O21: =IF(ISNUMBER(N21),IF(N21<=FormulaTest_Tolerance,"PASS","FAIL"),"FAIL") -> PASS | P21: CRE52.10, .18; CRR Art. 275(1), (2)
C22: Normal CDF(1.96) | D22: x | E22: 1.96 | L22: =_xlfn.NORM.S.DIST($E22,TRUE) -> 0.9750021 | M22: {=SACCR_NormCDF($E22)} -> 0.9750021 | N22: =IFERROR(ABS(M22-L22)/MAX(1,ABS(L22)),"") -> 0 | O22: =IF(ISNUMBER(N22),IF(N22<=FormulaTest_Tolerance,"PASS","FAIL"),"FAIL") -> PASS | P22: Standard normal distribution
C23: Normal CDF(-4) | D23: x | E23: -4 | L23: =_xlfn.NORM.S.DIST($E23,TRUE) -> 3.1671242e-05 | M23: {=SACCR_NormCDF($E23)} -> 3.1671242e-05 | N23: =IFERROR(ABS(M23-L23)/MAX(1,ABS(L23)),"") -> 3.8489177e-18 | O23: =IF(ISNUMBER(N23),IF(N23<=FormulaTest_Tolerance,"PASS","FAIL"),"FAIL") -> PASS | P23: Standard normal distribution
C24: CRR lambda IR, P=-0.20% K=0.10% | D24: P, K, interest rate | E24: -0.002 | F24: 0.001 | G24: TRUE | L24: =IF($G24,MAX(0.001-MIN($E24,$F24),0),MAX(-(1+0.1)*MIN($E24,$F24),0)) -> 0.003 | M24: {=SACCR_LambdaCRR($E24,$F24,$G24)} -> 0.003 | N24: =IFERROR(ABS(M24-L24)/MAX(1,ABS(L24)),"") -> 0 | O24: =IF(ISNUMBER(N24),IF(N24<=FormulaTest_Tolerance,"PASS","FAIL"),"FAIL") -> PASS | P24: CRR-RTS Art. 5(2)
C25: CRR lambda IR, P=2% K=3% (no shift) | D25: P, K, interest rate | E25: 0.02 | F25: 0.03 | G25: TRUE | L25: =IF($G25,MAX(0.001-MIN($E25,$F25),0),MAX(-(1+0.1)*MIN($E25,$F25),0)) -> 0 | M25: {=SACCR_LambdaCRR($E25,$F25,$G25)} -> 0 | N25: =IFERROR(ABS(M25-L25)/MAX(1,ABS(L25)),"") -> 0 | O25: =IF(ISNUMBER(N25),IF(N25<=FormulaTest_Tolerance,"PASS","FAIL"),"FAIL") -> PASS | P25: CRR-RTS Art. 5(2)
C26: CRR lambda IR, P=0.05% K=1% (to threshold) | D26: P, K, interest rate | E26: 0.0005 | F26: 0.01 | G26: TRUE | L26: =IF($G26,MAX(0.001-MIN($E26,$F26),0),MAX(-(1+0.1)*MIN($E26,$F26),0)) -> 0.0005 | M26: {=SACCR_LambdaCRR($E26,$F26,$G26)} -> 0.0005 | N26: =IFERROR(ABS(M26-L26)/MAX(1,ABS(L26)),"") -> 0 | O26: =IF(ISNUMBER(N26),IF(N26<=FormulaTest_Tolerance,"PASS","FAIL"),"FAIL") -> PASS | P26: CRR-RTS Art. 5(2)
C27: CRR lambda commodity, P=-5 K=-4 | D27: P, K, interest rate | E27: -5 | F27: -4 | G27: FALSE | L27: =IF($G27,MAX(0.001-MIN($E27,$F27),0),MAX(-(1+0.1)*MIN($E27,$F27),0)) -> 5.5 | M27: {=SACCR_LambdaCRR($E27,$F27,$G27)} -> 5.5 | N27: =IFERROR(ABS(M27-L27)/MAX(1,ABS(L27)),"") -> 0 | O27: =IF(ISNUMBER(N27),IF(N27<=FormulaTest_Tolerance,"PASS","FAIL"),"FAIL") -> PASS | P27: CRR-RTS Art. 5(2)
C28: CRR lambda commodity, P=40 K=35 (no shift) | D28: P, K, interest rate | E28: 40 | F28: 35 | G28: FALSE | L28: =IF($G28,MAX(0.001-MIN($E28,$F28),0),MAX(-(1+0.1)*MIN($E28,$F28),0)) -> 0 | M28: {=SACCR_LambdaCRR($E28,$F28,$G28)} -> 0 | N28: =IFERROR(ABS(M28-L28)/MAX(1,ABS(L28)),"") -> 0 | O28: =IF(ISNUMBER(N28),IF(N28<=FormulaTest_Tolerance,"PASS","FAIL"),"FAIL") -> PASS | P28: CRR-RTS Art. 5(2)

Sheet Basel_vs_CRR
B1: K-SACCR
B2: Basel CRE52 vs EU CRR
C3: EU text: CRR consolidated version of 26/06/2026 (Art. 273a-282), Delegated Regulation (EU) 2021/931 as amended by (EU) 2025/855, EBA Q&A. Basel: CRE52, its FAQs and the CRE99 / BCBS 279 examples.
C5: # | D5: Area | E5: Basel CRE52 | F5: EU CRR | G5: Same / different | H5: Effect on numbers | I5: Workbook treatment | J5: Tests | K5: Source check (text, not numerical validation)
C6: 1 | D6: Normative hierarchy | E6: CRE52 + CRE52 FAQs; CRE99 / BCBS 279 Annex 4a worked examples. | F6: CRR Art. 273a-282 (Level 1) -> Delegated Reg. (EU) 2021/931 as amended (incl. 2025/855) -> EBA Q&A. | G6: Different | H6: Interpretation route | I6: Regime on Params (default CRR), override per netting set. The engine applies each regime's rules; the SACCR_* functions take no regime argument (SACCR_LambdaCRR is the CRR lambda). | J6: - | K6: VERIFIED
C7: 2 | D7: EAD and alpha | E7: EAD = 1.4 x (RC + PFE) [CRE52.1]. | F7: Art. 274(2): alpha = 1.4; the consolidated text has no alpha exception by counterparty type. | G7: Same | H7: None | I7: Common core. Alpha override per netting set exists only for what-if use. | J7: T04 | K7: VERIFIED
C8: 3 | D8: Cap of margined EAD | E8: Capped at the EAD of the same netting set "calculated on an unmargined basis" [CRE52.2]; unmargined C is the NICA collateral [CRE52.10], so the cap uses NICA only. | F8: Art. 274(3): capped at the exposure of the same netting set "not subject to any form of margin agreement". RC per Art. 275(1); NICA does not include VM posted or received (EBA Q&A 2023_6962, final, 15/03/2024). | G8: Same | H8: None: both caps use NICA (posted-VM scenario ~41m in both regimes). | I8: Implemented: the cap uses C = NICA in both regimes. Results keeps the margined C, RC, add-ons, multiplier and PFE in their ordinary columns and shows the cap basis in its own columns (EAD cap, C, RC and multiplier on the cap basis, unmargined add-on); EAD is the lower of the two, with Cap applied = Y when the cap binds. | J8: T15-T18 | K8: VERIFIED (CRE52.2, CRE52.10; CRR, Q&A)
C9: 4 | D9: RC - unmargined | E9: RC = max(V - C, 0) [CRE52.10]; a one-way agreement where only the bank posts VM is unmargined, and C includes that VM with a negative sign [CRE52.2, CRE52.10 footnote 2]. | F9: RC = max(CMV - NICA, 0) [Art. 275(1)]; collateral per CRR definitions (Art. 272(12a), 276). A one-way margin agreement is a margin agreement [Art. 272(7a)]: the netting set is margined. | G9: Different (one-way agreement) | H9: One-way agreements where the bank posts VM | I9: Enter collateral after haircuts, in NICA. VM held on an unmargined set is rejected. VM posted (one-way agreement): BCBS includes it in C; CRR rejects it - set Margined = Y. | J9: T08 | K9: VERIFIED
C10: 5 | D10: RC - margined | E10: RC = max(V - C, TH + MTA - NICA, 0) [CRE52.18]. | F10: RC = max(CMV - VM - NICA, TH + MTA - NICA, 0) [Art. 275(2)]. | G10: Same | H10: None | I10: Common core. | J10: T14 | K10: VERIFIED
C11: 6 | D11: Multiplier | E11: min(1; 5% + 95% exp((V - C) / (2 x 95% x AddOn))) [CRE52.23]. | F11: Art. 278(3): same; z = CMV - VM - NICA (margined), CMV - NICA (unmargined). | G11: Same | H11: None | I11: Common core. | J11: T05, T13 | K11: VERIFIED
C12: 7 | D12: Asset classes | E12: Five: IR, FX, credit, equity, commodity. | F12: Six: adds "other risks" [Art. 277(1)(f)]. | G12: Different | H12: Additional add-on | I12: Asset class OT, allowed only in CRR netting sets; rejected (Checks) under BCBS. | J12: T24-T26 | K12: VERIFIED
C13: 8 | D13: Other-risks add-on | E13: No equivalent. | F13: Art. 280f: per hedging set, AddOn = coefficient x 8% x |effective notional|; supervisory option volatility 150% [Art. 279a Table 1]. | G13: EU only | H13: New add-on | I13: Hedging set per primary risk driver (risk-factor text) and nature; FX-style aggregation. | J13: T24, T25 | K13: VERIFIED (SF, vol; one hedging set per identical primary risk driver, Art. 277a(1)(f))
C14: 9 | D14: Risk-driver mapping | E14: Primary risk driver; for complex trades supervisors may require allocation to more than one class. | F14: Art. 277(2)-(3): one vs several material risk drivers, mapped once per risk category; method fixed in Delegated Reg. (EU) 2021/931. | G14: Different (EU prescriptive) | H14: Classification of hybrids | I14: Not automated: enter one leg per risk category, classified per the RTS, all with the same Economic trade ID; the MtM leg (Y) carries the trade's MtM and every other leg 0, which the engine enforces. | J14: - | K14: VERIFIED
C15: 10 | D15: Commodity hedging sets | E15: Energy, metals, agricultural, other [CRE52.70]; no specific rule for weather. | F15: Energy, metals, agricultural goods, other, climatic conditions [Art. 277a]; climatic variables mapped to commodity [Art. 277(4)(b)]. | G15: Different | H15: Climatic trades no longer offset against "other" | I15: CO sub-class CLIMATIC (CRR-only row, own hedging set). | J15: T27 | K15: VERIFIED: 18% [Art. 280e(5)]
C16: 11 | D16: Inflation | E16: Basel FAQ: interest-rate class, separate hedging set per currency, SF 0.5%. | F16: Mapped to interest rate. | G16: Same numbers | H16: None expected | I16: Enter as IR; a distinct risk-factor label (e.g. EUR-INFL) gives a separate hedging set. | J16: - | K16: VERIFIED (CRR Art. 277(4)(a), 277a(1))
C17: 12 | D17: Option delta - negative rates / prices | E17: IR options where P or K is zero or negative: shift price and strike by lambda, the presumed lowest extent to which rates in that currency can become negative, the same for all IR options in the currency; supervisors may recommend it per currency, banks may use lower values [CRE52.40 FAQ2]. No shift is defined for other options. | F17: Delegated Reg. 2021/931 Art. 5 (am. 2025/855), per option: IR lambda = max(0.10% - min(P,K); 0); commodity lambda = max(-(1 + 0.1) x min(P,K); 0). | G17: Different | H17: Delta differs when P or K is near or below zero | I17: CRR IR and commodity options: the RTS lambda is computed; a different value entered is ignored with a warning. BCBS IR options: lambda is entered per trade; one value per currency is the user's to ensure and is not checked. Other options (under BCBS, commodity options too): an entered lambda is accepted as a technical shift, which is not proof of regulatory permission. Rejected if P + lambda or K + lambda <= 0. | J17: T20-T23 | K17: VERIFIED (EBA/RTS/2024/16; OJ 2025/855)
... C33: 28 | D33: Multiple exchanges and leverage | E33: Leveraged swaps at the equivalent unleveraged notional; notional x number of exchanges of principal in the contract [CRE52.37(3)-(4)]. | F33: Notional x number of remaining payments for multiple notional exchanges; multiplied cash flows or underlyings adjusted [Art. 279b(2)(b), (c)]. | G33: Different | H33: Counted: exchanges in the contract (BCBS), remaining payments (CRR) | I33: Enter the adjusted notional per regime; count principal exchanges or payments as the rule says, not every coupon. | J33: - | K33: VERIFIED
